<?xml version="1.0" encoding="UTF-8" ?><document><annotations itct="CAAQwOYBIhMI15_agcnu3wIVGtpVCh3_cgR_KPgdMgJpdkiDmL7Um4Tqvls">
<annotation id="annotation_1070642451" type="text" style="highlightText" logable="false" itct="">
  
  <segment spaceRelative="annotation_2565354617">
    <movingRegion type="rect">
      <rectRegion x="0.00000" y="29.72200" w="25.00000" h="6.00000" t="never"/>
      <rectRegion x="0.00000" y="29.72200" w="25.00000" h="6.00000" t="never"/>
    </movingRegion>
  </segment>
  <appearance bgAlpha="0" textSize="3.911599999999999" highlightFontColor="0"/>
  <trigger>
    <condition ref="annotation_2565354617" state="rollOver"/>
  </trigger>
</annotation>

<annotation id="annotation_250261423" type="text" style="highlightText" logable="false" itct="">
  
  <segment spaceRelative="annotation_2796847907">
    <movingRegion type="rect">
      <rectRegion x="0.00000" y="29.72200" w="25.00000" h="6.00000" t="never"/>
      <rectRegion x="0.00000" y="29.72200" w="25.00000" h="6.00000" t="never"/>
    </movingRegion>
  </segment>
  <appearance bgAlpha="0" textSize="3.911599999999999" highlightFontColor="0"/>
  <trigger>
    <condition ref="annotation_2796847907" state="rollOver"/>
  </trigger>
</annotation>

<annotation id="annotation_2565354617" type="highlight" log_data="ei=ly49XJf4O5q01wL_5ZH4Bw&amp;link=http%3A%2F%2Fwww.youtube.com%2Fuser%2Fspacefrogsent&amp;a-v=W32oIbqPjAM&amp;a-id=annotation_2565354617&amp;l-class=3&amp;xble=1&amp;a-type=3" itct="CAEQs-UBGP___________wEiEwjXn9qBye7fAhUa2lUKHf9yBH8o-B0yAml2SIOYvtSbhOq-Ww">
  <segment>
    <movingRegion type="rect">
      <rectRegion x="10.07100" y="35.11300" w="15.72000" h="26.64800" t="6:25.811"/>
      <rectRegion x="10.07100" y="35.11300" w="15.72000" h="26.64800" t="6:46.116"/>
    </movingRegion>
  </segment>
  <appearance bgColor="16777215" highlightWidth="3" borderAlpha="0.2"/>
  
  <action type="openUrl" trigger="click">
    <url target="new" value="https://www.youtube.com/user/spacefrogsent?annotation_id=annotation_2565354617&amp;ei=ly49XJf4O5q01wL_5ZH4Bw&amp;feature=iv&amp;src_vid=W32oIbqPjAM" link_class="3"/>
  </action>

</annotation>

<annotation id="annotation_2649294219" type="text" style="highlightText" logable="false" itct="">
  
  <segment spaceRelative="annotation_2704913611">
    <movingRegion type="rect">
      <rectRegion x="0.00000" y="29.72200" w="25.00000" h="6.00000" t="never"/>
      <rectRegion x="0.00000" y="29.72200" w="25.00000" h="6.00000" t="never"/>
    </movingRegion>
  </segment>
  <appearance bgAlpha="0" textSize="3.911599999999999" highlightFontColor="0"/>
  <trigger>
    <condition ref="annotation_2704913611" state="rollOver"/>
  </trigger>
</annotation>

<annotation id="annotation_2704913611" type="highlight" log_data="ei=ly49XJf4O5q01wL_5ZH4Bw&amp;link=http%3A%2F%2Fwww.youtube.com%2Fwatch%3Fv%3DO3p6Q8Wj9g4&amp;a-v=W32oIbqPjAM&amp;a-id=annotation_2704913611&amp;l-class=1&amp;xble=1&amp;a-type=3" itct="CAIQs-UBGP___________wEiEwjXn9qBye7fAhUa2lUKHf9yBH8o-B0yAml2SIOYvtSbhOq-Ww">
  <segment>
    <movingRegion type="rect">
      <rectRegion x="57.75300" y="4.50700" w="40.19000" h="42.23900" t="6:25.811"/>
      <rectRegion x="57.75300" y="4.50700" w="40.19000" h="42.23900" t="6:46.116"/>
    </movingRegion>
  </segment>
  <appearance bgColor="16777215" highlightWidth="3" borderAlpha="0.2"/>
  
  <action type="openUrl" trigger="click">
    <url target="current" value="https://www.youtube.com/watch?annotation_id=annotation_2704913611&amp;ei=ly49XJf4O5q01wL_5ZH4Bw&amp;feature=iv&amp;src_vid=W32oIbqPjAM&amp;v=O3p6Q8Wj9g4" link_class="1"/>
  </action>

</annotation>

<annotation id="annotation_2796847907" type="highlight" log_data="ei=ly49XJf4O5q01wL_5ZH4Bw&amp;link=http%3A%2F%2Fwww.youtube.com%2Fuser%2Fspacefrogsradio&amp;a-v=W32oIbqPjAM&amp;a-id=annotation_2796847907&amp;l-class=3&amp;xble=1&amp;a-type=3" itct="CAMQs-UBGP___________wEiEwjXn9qBye7fAhUa2lUKHf9yBH8o-B0yAml2SIOYvtSbhOq-Ww">
  <segment>
    <movingRegion type="rect">
      <rectRegion x="29.90500" y="33.80300" w="14.66000" h="25.52100" t="6:25.811"/>
      <rectRegion x="29.90500" y="33.80300" w="14.66000" h="25.52100" t="6:46.116"/>
    </movingRegion>
  </segment>
  <appearance bgColor="16777215" highlightWidth="3" borderAlpha="0.2"/>
  
  <action type="openUrl" trigger="click">
    <url target="new" value="https://www.youtube.com/user/spacefrogsradio?annotation_id=annotation_2796847907&amp;ei=ly49XJf4O5q01wL_5ZH4Bw&amp;feature=iv&amp;src_vid=W32oIbqPjAM" link_class="3"/>
  </action>

</annotation>

<annotation id="annotation_4206349069" type="highlight" log_data="ei=ly49XJf4O5q01wL_5ZH4Bw&amp;link=http%3A%2F%2Fwww.youtube.com%2Fwatch%3Fv%3DINMNhvTO5BM&amp;a-v=W32oIbqPjAM&amp;a-id=annotation_4206349069&amp;l-class=1&amp;xble=1&amp;a-type=3" itct="CAQQs-UBGP___________wEiEwjXn9qBye7fAhUa2lUKHf9yBH8o-B0yAml2SIOYvtSbhOq-Ww">
  <segment>
    <movingRegion type="rect">
      <rectRegion x="54.48600" y="52.39400" w="37.44500" h="39.60600" t="6:25.811"/>
      <rectRegion x="54.48600" y="52.39400" w="37.44500" h="39.60600" t="6:46.116"/>
    </movingRegion>
  </segment>
  <appearance bgColor="16777215" highlightWidth="3" borderAlpha="0.2"/>
  
  <action type="openUrl" trigger="click">
    <url target="current" value="https://www.youtube.com/watch?annotation_id=annotation_4206349069&amp;ei=ly49XJf4O5q01wL_5ZH4Bw&amp;feature=iv&amp;src_vid=W32oIbqPjAM&amp;v=INMNhvTO5BM" link_class="1"/>
  </action>

</annotation>

<annotation id="annotation_925134915" type="text" style="highlightText" logable="false" itct="">
  
  <segment spaceRelative="annotation_4206349069">
    <movingRegion type="rect">
      <rectRegion x="0.00000" y="29.72200" w="25.00000" h="6.00000" t="never"/>
      <rectRegion x="0.00000" y="29.72200" w="25.00000" h="6.00000" t="never"/>
    </movingRegion>
  </segment>
  <appearance bgAlpha="0" textSize="3.911599999999999" highlightFontColor="0"/>
  <trigger>
    <condition ref="annotation_4206349069" state="rollOver"/>
  </trigger>
</annotation>
</annotations></document>