<?xml version="1.0" encoding="UTF-8" ?><document><annotations itct="CAAQwOYBIhMI8KLogf3u3wIVSTbgCh20ZgR6KPgdMgJpdkjPq73q1P67o4QB">
<annotation id="annotation_133874375" type="text" style="highlightText" logable="false" itct="">
  
  <segment spaceRelative="annotation_473303333">
    <movingRegion type="rect">
      <rectRegion x="1.26800" y="16.62000" w="25.00000" h="4.44400" t="never"/>
      <rectRegion x="1.26800" y="16.62000" w="25.00000" h="4.44400" t="never"/>
    </movingRegion>
  </segment>
  <appearance bgAlpha="0" textSize="3.911599999999999" highlightFontColor="15921906"/>
  <trigger>
    <condition ref="annotation_473303333" state="rollOver"/>
  </trigger>
</annotation>

<annotation id="annotation_1666044679" type="highlight" log_data="a-type=3&amp;a-v=hEbv9U1PVc8&amp;l-class=3&amp;link=http%3A%2F%2Fwww.youtube.com%2Fuser%2FLeFloid&amp;ei=HmU9XPCbNMnsgAe0zZHQBw&amp;xble=1&amp;a-id=annotation_1666044679" itct="CAEQs-UBGP___________wEiEwjwouiB_e7fAhVJNuAKHbRmBHoo-B0yAml2SM-rverU_rujhAE">
  <segment>
    <movingRegion type="rect">
      <rectRegion x="2.21900" y="10.70400" w="44.32800" h="67.67800" t="4:39.366"/>
      <rectRegion x="2.21900" y="10.70400" w="44.32800" h="67.67800" t="5:17.200"/>
    </movingRegion>
  </segment>
  <appearance bgColor="16777215" highlightWidth="3" borderAlpha="0.2"/>
  
  <action type="openUrl" trigger="click">
    <url target="new" value="https://www.youtube.com/user/LeFloid?annotation_id=annotation_1666044679&amp;ei=HmU9XPCbNMnsgAe0zZHQBw&amp;feature=iv&amp;src_vid=hEbv9U1PVc8" link_class="3"/>
  </action>

</annotation>

<annotation id="annotation_2072527417" type="text" style="highlightText" logable="false" itct="">
  
  <segment spaceRelative="annotation_3510307559">
    <movingRegion type="rect">
      <rectRegion x="0.00000" y="29.72200" w="25.00000" h="4.44400" t="never"/>
      <rectRegion x="0.00000" y="29.72200" w="25.00000" h="4.44400" t="never"/>
    </movingRegion>
  </segment>
  <appearance bgAlpha="0" textSize="3.911599999999999" highlightFontColor="15921906"/>
  <trigger>
    <condition ref="annotation_3510307559" state="rollOver"/>
  </trigger>
</annotation>

<annotation id="annotation_295250711" type="highlight" log_data="a-type=3&amp;a-v=hEbv9U1PVc8&amp;l-class=1&amp;link=http%3A%2F%2Fwww.youtube.com%2Fwatch%3Fv%3D4xK66MzhSlY&amp;ei=HmU9XPCbNMnsgAe0zZHQBw&amp;xble=1&amp;a-id=annotation_295250711" itct="CAIQs-UBGP___________wEiEwjwouiB_e7fAhVJNuAKHbRmBHoo-B0yAml2SM-rverU_rujhAE">
  <segment>
    <movingRegion type="rect">
      <rectRegion x="28.84300" y="91.36600" w="18.66100" h="8.63400" t="4:39.366"/>
      <rectRegion x="28.84300" y="91.36600" w="18.66100" h="8.63400" t="5:17.200"/>
    </movingRegion>
  </segment>
  <appearance bgColor="16777215" highlightWidth="3" borderAlpha="0.2"/>
  
  <action type="openUrl" trigger="click">
    <url target="new" value="https://www.youtube.com/watch?annotation_id=annotation_295250711&amp;ei=HmU9XPCbNMnsgAe0zZHQBw&amp;feature=iv&amp;src_vid=hEbv9U1PVc8&amp;v=4xK66MzhSlY" link_class="1"/>
  </action>

</annotation>

<annotation id="annotation_3510307559" type="highlight" log_data="a-type=3&amp;a-v=hEbv9U1PVc8&amp;l-class=1&amp;link=http%3A%2F%2Fwww.youtube.com%2Fwatch%3Fv%3DWyhTCItfaZA&amp;ei=HmU9XPCbNMnsgAe0zZHQBw&amp;xble=1&amp;a-id=annotation_3510307559" itct="CAMQs-UBGP___________wEiEwjwouiB_e7fAhVJNuAKHbRmBHoo-B0yAml2SM-rverU_rujhAE">
  <segment>
    <movingRegion type="rect">
      <rectRegion x="58.47900" y="91.93000" w="19.45300" h="8.07000" t="4:39.366"/>
      <rectRegion x="58.47900" y="91.93000" w="19.45300" h="8.07000" t="5:17.200"/>
    </movingRegion>
  </segment>
  <appearance bgColor="16777215" highlightWidth="3" borderAlpha="0.2"/>
  
  <action type="openUrl" trigger="click">
    <url target="current" value="https://www.youtube.com/watch?annotation_id=annotation_3510307559&amp;ei=HmU9XPCbNMnsgAe0zZHQBw&amp;feature=iv&amp;src_vid=hEbv9U1PVc8&amp;v=WyhTCItfaZA" link_class="1"/>
  </action>

</annotation>

<annotation id="annotation_4024215355" type="text" style="highlightText" logable="false" itct="">
  
  <segment spaceRelative="annotation_295250711">
    <movingRegion type="rect">
      <rectRegion x="0.00000" y="29.72200" w="25.00000" h="4.44400" t="never"/>
      <rectRegion x="0.00000" y="29.72200" w="25.00000" h="4.44400" t="never"/>
    </movingRegion>
  </segment>
  <appearance bgAlpha="0" textSize="3.911599999999999" highlightFontColor="15921906"/>
  <trigger>
    <condition ref="annotation_295250711" state="rollOver"/>
  </trigger>
</annotation>

<annotation id="annotation_4030096993" type="text" style="popup" log_data="a-type=1&amp;a-v=hEbv9U1PVc8&amp;l-class=5&amp;link=http%3A%2F%2Fwww.youtube.com%2Fsubscription_center%3Fadd_user%3DLeFloid&amp;ei=HmU9XPCbNMnsgAe0zZHQBw&amp;xble=1&amp;a-id=annotation_4030096993" itct="CAQQs-UBGP___________wEiEwjwouiB_e7fAhVJNuAKHbRmBHoo-B0yAml2SM-rverU_rujhAE">
  <TEXT>AboButton</TEXT>
  <segment>
    <movingRegion type="rect">
      <rectRegion x="0.00000" y="0.00000" w="15.57200" h="7.47200" t="0:00.000"/>
      <rectRegion x="0.00000" y="0.00000" w="15.57200" h="7.47200" t="4:38.380"/>
    </movingRegion>
  </segment>
  <appearance bgAlpha="0.25" bgColor="0" fgColor="16777215" textSize="3.3098083333333332" effects="">
    
  </appearance>
  
  <action type="openUrl" trigger="click">
    <url target="new" value="https://www.youtube.com/subscription_center?add_user=LeFloid&amp;annotation_id=annotation_4030096993&amp;ei=HmU9XPCbNMnsgAe0zZHQBw&amp;feature=iv&amp;src_vid=hEbv9U1PVc8" link_class="5"/>
  </action>

</annotation>
<annotation id="annotation_473303333" type="highlight" log_data="a-type=3&amp;a-v=hEbv9U1PVc8&amp;l-class=3&amp;link=http%3A%2F%2Fwww.youtube.com%2Fuser%2FDoktorFroid&amp;ei=HmU9XPCbNMnsgAe0zZHQBw&amp;xble=1&amp;a-id=annotation_473303333" itct="CAUQs-UBGP___________wEiEwjwouiB_e7fAhVJNuAKHbRmBHoo-B0yAml2SM-rverU_rujhAE">
  <segment>
    <movingRegion type="rect">
      <rectRegion x="67.35300" y="49.57700" w="30.54700" h="37.63400" t="4:39.366"/>
      <rectRegion x="67.35300" y="49.57700" w="30.54700" h="37.63400" t="5:17.200"/>
    </movingRegion>
  </segment>
  <appearance bgColor="16777215" highlightWidth="3" borderAlpha="0.2"/>
  
  <action type="openUrl" trigger="click">
    <url target="new" value="https://www.youtube.com/user/DoktorFroid?annotation_id=annotation_473303333&amp;ei=HmU9XPCbNMnsgAe0zZHQBw&amp;feature=iv&amp;src_vid=hEbv9U1PVc8" link_class="3"/>
  </action>

</annotation>

<annotation id="annotation_543392903" type="text" style="highlightText" logable="false" itct="">
  
  <segment spaceRelative="annotation_623460313">
    <movingRegion type="rect">
      <rectRegion x="3.01100" y="16.90100" w="25.00000" h="4.44400" t="never"/>
      <rectRegion x="3.01100" y="16.90100" w="25.00000" h="4.44400" t="never"/>
    </movingRegion>
  </segment>
  <appearance bgAlpha="0" textSize="3.911599999999999" highlightFontColor="15921906"/>
  <trigger>
    <condition ref="annotation_623460313" state="rollOver"/>
  </trigger>
</annotation>

<annotation id="annotation_623460313" type="highlight" log_data="a-type=3&amp;a-v=hEbv9U1PVc8&amp;l-class=3&amp;link=http%3A%2F%2Fwww.youtube.com%2Fuser%2FFlipFloid&amp;ei=HmU9XPCbNMnsgAe0zZHQBw&amp;xble=1&amp;a-id=annotation_623460313" itct="CAYQs-UBGP___________wEiEwjwouiB_e7fAhVJNuAKHbRmBHoo-B0yAml2SM-rverU_rujhAE">
  <segment>
    <movingRegion type="rect">
      <rectRegion x="67.19500" y="5.35200" w="30.70500" h="39.60600" t="4:39.366"/>
      <rectRegion x="67.19500" y="5.35200" w="30.70500" h="39.60600" t="5:17.200"/>
    </movingRegion>
  </segment>
  <appearance bgColor="16777215" highlightWidth="3" borderAlpha="0.2"/>
  
  <action type="openUrl" trigger="click">
    <url target="new" value="https://www.youtube.com/user/FlipFloid?annotation_id=annotation_623460313&amp;ei=HmU9XPCbNMnsgAe0zZHQBw&amp;feature=iv&amp;src_vid=hEbv9U1PVc8" link_class="3"/>
  </action>

</annotation>

<annotation id="annotation_701543235" type="text" style="highlightText" logable="false" itct="">
  
  <segment spaceRelative="annotation_1666044679">
    <movingRegion type="rect">
      <rectRegion x="7.92400" y="32.11300" w="25.00000" h="4.44400" t="never"/>
      <rectRegion x="7.92400" y="32.11300" w="25.00000" h="4.44400" t="never"/>
    </movingRegion>
  </segment>
  <appearance bgAlpha="0" textSize="3.911599999999999" highlightFontColor="15921906"/>
  <trigger>
    <condition ref="annotation_1666044679" state="rollOver"/>
  </trigger>
</annotation>
</annotations></document>