<?xml version="1.0" encoding="UTF-8" ?><document><annotations itct="CAAQwOYBIhMI4biC4vzu3wIVlKLeCh0ErQcyKPgdMgJpdkielLTh9vzexlM">
<annotation id="annotation_1279082083" type="text" style="highlightText" logable="false" itct="">
  
  <segment spaceRelative="annotation_36010531">
    <movingRegion type="rect">
      <rectRegion x="0.00000" y="29.72200" w="25.00000" h="6.00000" t="never"/>
      <rectRegion x="0.00000" y="29.72200" w="25.00000" h="6.00000" t="never"/>
    </movingRegion>
  </segment>
  <appearance bgAlpha="0" textSize="3.911599999999999" highlightFontColor="0"/>
  <trigger>
    <condition ref="annotation_36010531" state="rollOver"/>
  </trigger>
</annotation>

<annotation id="annotation_1991472431" type="text" style="highlightText" logable="false" itct="">
  
  <segment spaceRelative="annotation_2436004549">
    <movingRegion type="rect">
      <rectRegion x="0.00000" y="29.72200" w="25.00000" h="6.00000" t="never"/>
      <rectRegion x="0.00000" y="29.72200" w="25.00000" h="6.00000" t="never"/>
    </movingRegion>
  </segment>
  <appearance bgAlpha="0" textSize="3.911599999999999" highlightFontColor="0"/>
  <trigger>
    <condition ref="annotation_2436004549" state="rollOver"/>
  </trigger>
</annotation>

<annotation id="annotation_226466033" type="highlight" log_data="ei=3GQ9XOHaCpTF-gaE2p6QAw&amp;a-id=annotation_226466033&amp;a-type=3&amp;link=http%3A%2F%2Fwww.youtube.com%2Fuser%2FFlipFloid&amp;xble=1&amp;l-class=3&amp;a-v=U41752wtCh4" itct="CAEQs-UBGP___________wEiEwjhuILi_O7fAhWUot4KHQStBzIo-B0yAml2SJ6UtOH2_N7GUw">
  <segment>
    <movingRegion type="rect">
      <rectRegion x="67.82900" y="5.35200" w="30.23000" h="38.47900" t="5:01.022"/>
      <rectRegion x="67.82900" y="5.35200" w="30.23000" h="38.47900" t="5:36.720"/>
    </movingRegion>
  </segment>
  <appearance bgColor="16777215" highlightWidth="3" borderAlpha="0.2"/>
  
  <action type="openUrl" trigger="click">
    <url target="new" value="https://www.youtube.com/user/FlipFloid?annotation_id=annotation_226466033&amp;ei=3GQ9XOHaCpTF-gaE2p6QAw&amp;feature=iv&amp;src_vid=U41752wtCh4" link_class="3"/>
  </action>

</annotation>

<annotation id="annotation_2436004549" type="highlight" log_data="ei=3GQ9XOHaCpTF-gaE2p6QAw&amp;a-id=annotation_2436004549&amp;a-type=3&amp;link=http%3A%2F%2Fwww.youtube.com%2Fwatch%3Fv%3Dvwm7zWOW7kM%26list%3DUULm6s42r_wCbBX0QqXNCTwg&amp;xble=1&amp;l-class=1&amp;a-v=U41752wtCh4" itct="CAIQs-UBGP___________wEiEwjhuILi_O7fAhWUot4KHQStBzIo-B0yAml2SJ6UtOH2_N7GUw">
  <segment>
    <movingRegion type="rect">
      <rectRegion x="57.68600" y="90.52100" w="18.81900" h="9.47900" t="5:01.022"/>
      <rectRegion x="57.68600" y="90.52100" w="18.81900" h="9.47900" t="5:36.720"/>
    </movingRegion>
  </segment>
  <appearance bgColor="16777215" highlightWidth="3" borderAlpha="0.2"/>
  
  <action type="openUrl" trigger="click">
    <url target="new" value="https://www.youtube.com/watch?annotation_id=annotation_2436004549&amp;ei=3GQ9XOHaCpTF-gaE2p6QAw&amp;feature=iv&amp;list=UULm6s42r_wCbBX0QqXNCTwg&amp;src_vid=U41752wtCh4&amp;v=vwm7zWOW7kM" link_class="1"/>
  </action>

</annotation>

<annotation id="annotation_2659939279" type="text" style="popup" log_data="ei=3GQ9XOHaCpTF-gaE2p6QAw&amp;a-id=annotation_2659939279&amp;a-type=1&amp;link=http%3A%2F%2Fwww.youtube.com%2Fuser%2FLeFloid%3Fsub_confirmation%3D1&amp;xble=1&amp;l-class=5&amp;a-v=U41752wtCh4" itct="CAMQs-UBGP___________wEiEwjhuILi_O7fAhWUot4KHQStBzIo-B0yAml2SJ6UtOH2_N7GUw">
  <TEXT>ABO-KNOPP!</TEXT>
  <segment>
    <movingRegion type="rect">
      <rectRegion x="0.00000" y="0.00000" w="17.31400" h="6.91500" t="0:00.000"/>
      <rectRegion x="0.00000" y="0.00000" w="17.31400" h="6.91500" t="4:59.935"/>
    </movingRegion>
  </segment>
  <appearance bgAlpha="0.25" bgColor="0" fgColor="16777215" textSize="3.3098083333333332" effects="">
    
  </appearance>
  
  <action type="openUrl" trigger="click">
    <url target="new" value="https://www.youtube.com/user/LeFloid?annotation_id=annotation_2659939279&amp;ei=3GQ9XOHaCpTF-gaE2p6QAw&amp;feature=iv&amp;src_vid=U41752wtCh4&amp;sub_confirmation=1" link_class="5"/>
  </action>

</annotation>
<annotation id="annotation_3273359525" type="text" style="highlightText" logable="false" itct="">
  
  <segment spaceRelative="annotation_3995303217">
    <movingRegion type="rect">
      <rectRegion x="0.00000" y="29.72200" w="25.00000" h="6.00000" t="never"/>
      <rectRegion x="0.00000" y="29.72200" w="25.00000" h="6.00000" t="never"/>
    </movingRegion>
  </segment>
  <appearance bgAlpha="0" textSize="3.911599999999999" highlightFontColor="0"/>
  <trigger>
    <condition ref="annotation_3995303217" state="rollOver"/>
  </trigger>
</annotation>

<annotation id="annotation_335284913" type="text" style="popup" log_data="ei=3GQ9XOHaCpTF-gaE2p6QAw&amp;a-id=annotation_335284913&amp;a-type=1&amp;link=http%3A%2F%2Fwww.youtube.com%2Fuser%2FDoktorFroid&amp;xble=1&amp;l-class=3&amp;a-v=U41752wtCh4" itct="CAQQs-UBGP___________wEiEwjhuILi_O7fAhWUot4KHQStBzIo-B0yAml2SJ6UtOH2_N7GUw">
  <TEXT>Nerd-Knopp</TEXT>
  <segment>
    <movingRegion type="rect">
      <rectRegion x="17.27400" y="0.00000" w="16.52100" h="6.91500" t="0:00.000"/>
      <rectRegion x="17.27400" y="0.00000" w="16.52100" h="6.91500" t="4:59.935"/>
    </movingRegion>
  </segment>
  <appearance bgAlpha="0.25" bgColor="0" fgColor="16777215" textSize="3.3098083333333332" effects="">
    
  </appearance>
  
  <action type="openUrl" trigger="click">
    <url target="new" value="https://www.youtube.com/user/DoktorFroid?annotation_id=annotation_335284913&amp;ei=3GQ9XOHaCpTF-gaE2p6QAw&amp;feature=iv&amp;src_vid=U41752wtCh4" link_class="3"/>
  </action>

</annotation>
<annotation id="annotation_36010531" type="highlight" log_data="ei=3GQ9XOHaCpTF-gaE2p6QAw&amp;a-id=annotation_36010531&amp;a-type=3&amp;link=http%3A%2F%2Fwww.youtube.com%2Fuser%2FLeFloid&amp;xble=1&amp;l-class=3&amp;a-v=U41752wtCh4" itct="CAUQs-UBGP___________wEiEwjhuILi_O7fAhWUot4KHQStBzIo-B0yAml2SJ6UtOH2_N7GUw">
  <segment>
    <movingRegion type="rect">
      <rectRegion x="2.37700" y="10.70400" w="45.21100" h="66.35500" t="5:01.022"/>
      <rectRegion x="2.37700" y="10.70400" w="45.21100" h="66.35500" t="5:36.720"/>
    </movingRegion>
  </segment>
  <appearance bgColor="16777215" highlightWidth="3" borderAlpha="0.2"/>
  
  <action type="openUrl" trigger="click">
    <url target="new" value="https://www.youtube.com/user/LeFloid?annotation_id=annotation_36010531&amp;ei=3GQ9XOHaCpTF-gaE2p6QAw&amp;feature=iv&amp;src_vid=U41752wtCh4" link_class="3"/>
  </action>

</annotation>

<annotation id="annotation_3748514485" type="text" style="highlightText" logable="false" itct="">
  
  <segment spaceRelative="annotation_226466033">
    <movingRegion type="rect">
      <rectRegion x="0.00000" y="29.72200" w="25.00000" h="6.00000" t="never"/>
      <rectRegion x="0.00000" y="29.72200" w="25.00000" h="6.00000" t="never"/>
    </movingRegion>
  </segment>
  <appearance bgAlpha="0" textSize="3.911599999999999" highlightFontColor="0"/>
  <trigger>
    <condition ref="annotation_226466033" state="rollOver"/>
  </trigger>
</annotation>

<annotation id="annotation_3995303217" type="highlight" log_data="ei=3GQ9XOHaCpTF-gaE2p6QAw&amp;a-id=annotation_3995303217&amp;a-type=3&amp;link=http%3A%2F%2Fwww.youtube.com%2Fuser%2FDoktorFroid&amp;xble=1&amp;l-class=3&amp;a-v=U41752wtCh4" itct="CAYQs-UBGP___________wEiEwjhuILi_O7fAhWUot4KHQStBzIo-B0yAml2SJ6UtOH2_N7GUw">
  <segment>
    <movingRegion type="rect">
      <rectRegion x="67.51200" y="48.45100" w="29.91300" h="37.63400" t="5:01.022"/>
      <rectRegion x="67.51200" y="48.45100" w="29.91300" h="37.63400" t="5:36.720"/>
    </movingRegion>
  </segment>
  <appearance bgColor="16777215" highlightWidth="3" borderAlpha="0.2"/>
  
  <action type="openUrl" trigger="click">
    <url target="current" value="https://www.youtube.com/user/DoktorFroid?annotation_id=annotation_3995303217&amp;ei=3GQ9XOHaCpTF-gaE2p6QAw&amp;feature=iv&amp;src_vid=U41752wtCh4" link_class="3"/>
  </action>

</annotation>

<annotation id="annotation_423755685" type="highlight" log_data="ei=3GQ9XOHaCpTF-gaE2p6QAw&amp;a-id=annotation_423755685&amp;a-type=3&amp;link=http%3A%2F%2Fwww.youtube.com%2Fwatch%3Fv%3DmwSOtsf1vws%26list%3DPL2Ufja2qoGV6xdjvGiGqRDC3oy6XT802j&amp;xble=1&amp;l-class=1&amp;a-v=U41752wtCh4" itct="">
  <segment>
    <movingRegion type="rect">
      <rectRegion x="29.63500" y="90.52100" w="17.55200" h="9.47900" t="5:01.022"/>
      <rectRegion x="29.63500" y="90.52100" w="17.55200" h="9.47900" t="5:36.720"/>
    </movingRegion>
  </segment>
  <appearance bgColor="16777215" highlightWidth="3" borderAlpha="0.2"/>
  
  <action type="openUrl" trigger="click">
    <url target="new" value="https://www.youtube.com/watch?annotation_id=annotation_423755685&amp;ei=3GQ9XOHaCpTF-gaE2p6QAw&amp;feature=iv&amp;list=PL2Ufja2qoGV6xdjvGiGqRDC3oy6XT802j&amp;src_vid=U41752wtCh4&amp;v=mwSOtsf1vws" link_class="1"/>
  </action>

</annotation>

<annotation id="annotation_834459775" type="text" style="highlightText" logable="false" itct="">
  
  <segment spaceRelative="annotation_423755685">
    <movingRegion type="rect">
      <rectRegion x="0.00000" y="29.72200" w="25.00000" h="6.00000" t="never"/>
      <rectRegion x="0.00000" y="29.72200" w="25.00000" h="6.00000" t="never"/>
    </movingRegion>
  </segment>
  <appearance bgAlpha="0" textSize="3.911599999999999" highlightFontColor="0"/>
  <trigger>
    <condition ref="annotation_423755685" state="rollOver"/>
  </trigger>
</annotation>
</annotations></document>