<?xml version="1.0" encoding="UTF-8" ?><document><annotations itct="CAAQwOYBIhMI8Jfxpv3u3wIVyhTgCh1oaAhVKPgdMgJpdkjWl5y4xZXKmV4">
<annotation id="annotation_1070887645" type="highlight" log_data="l-class=3&amp;link=http%3A%2F%2Fwww.youtube.com%2Fuser%2FFlipFloid&amp;a-type=3&amp;a-v=XjMorFcHC9Y&amp;a-id=annotation_1070887645&amp;ei=bGU9XPCxJMqpgAfo0KGoBQ&amp;xble=1" itct="CAEQs-UBGP___________wEiEwjwl_Gm_e7fAhXKFOAKHWhoCFUo-B0yAml2SNaXnLjFlcqZXg">
  <segment>
    <movingRegion type="rect">
      <rectRegion x="68.93800" y="65.91500" w="25.00000" h="27.77800" t="4:21.796"/>
      <rectRegion x="68.93800" y="65.91500" w="25.00000" h="27.77800" t="4:57.494"/>
    </movingRegion>
  </segment>
  <appearance bgColor="16777215" highlightWidth="3" borderAlpha="0.2"/>
  
  <action type="openUrl" trigger="click">
    <url target="new" value="https://www.youtube.com/user/FlipFloid?annotation_id=annotation_1070887645&amp;ei=bGU9XPCxJMqpgAfo0KGoBQ&amp;feature=iv&amp;src_vid=XjMorFcHC9Y" link_class="3"/>
  </action>

</annotation>

<annotation id="annotation_1973692467" type="text" style="highlightText" logable="false" itct="">
  
  <segment spaceRelative="annotation_819645961">
    <movingRegion type="rect">
      <rectRegion x="0.00000" y="29.72200" w="25.00000" h="6.00000" t="never"/>
      <rectRegion x="0.00000" y="29.72200" w="25.00000" h="6.00000" t="never"/>
    </movingRegion>
  </segment>
  <appearance bgAlpha="0" textSize="3.911599999999999" highlightFontColor="0"/>
  <trigger>
    <condition ref="annotation_819645961" state="rollOver"/>
  </trigger>
</annotation>

<annotation id="annotation_2047159809" type="highlight" log_data="l-class=5&amp;link=http%3A%2F%2Fwww.youtube.com%2Fuser%2FLeFloid%3Fsub_confirmation%3D1&amp;a-type=3&amp;a-v=XjMorFcHC9Y&amp;a-id=annotation_2047159809&amp;ei=bGU9XPCxJMqpgAfo0KGoBQ&amp;xble=1" itct="CAIQs-UBGP___________wEiEwjwl_Gm_e7fAhXKFOAKHWhoCFUo-B0yAml2SNaXnLjFlcqZXg">
  <segment>
    <movingRegion type="rect">
      <rectRegion x="5.07100" y="3.66200" w="54.31900" h="52.28200" t="4:21.796"/>
      <rectRegion x="5.07100" y="3.66200" w="54.31900" h="52.28200" t="4:57.494"/>
    </movingRegion>
  </segment>
  <appearance bgColor="16777215" highlightWidth="3" borderAlpha="0.2"/>
  
  <action type="openUrl" trigger="click">
    <url target="new" value="https://www.youtube.com/user/LeFloid?annotation_id=annotation_2047159809&amp;ei=bGU9XPCxJMqpgAfo0KGoBQ&amp;feature=iv&amp;src_vid=XjMorFcHC9Y&amp;sub_confirmation=1" link_class="5"/>
  </action>

</annotation>

<annotation id="annotation_2115035321" type="highlight" log_data="l-class=5&amp;link=https%3A%2F%2Fwww.youtube.com%2Fchannel%2FUCidly38Zlq6tfx6voNAHQoA%3Fsub_confirmation%3D1&amp;a-type=3&amp;a-v=XjMorFcHC9Y&amp;a-id=annotation_2115035321&amp;ei=bGU9XPCxJMqpgAfo0KGoBQ&amp;xble=1" itct="CAMQs-UBGP___________wEiEwjwl_Gm_e7fAhXKFOAKHWhoCFUo-B0yAml2SNaXnLjFlcqZXg">
  <segment>
    <movingRegion type="rect">
      <rectRegion x="69.09700" y="33.52100" w="25.00000" h="27.77800" t="4:21.796"/>
      <rectRegion x="69.09700" y="33.52100" w="25.00000" h="27.77800" t="4:57.494"/>
    </movingRegion>
  </segment>
  <appearance bgColor="16777215" highlightWidth="3" borderAlpha="0.2"/>
  
  <action type="openUrl" trigger="click">
    <url target="new" value="https://www.youtube.com/channel/UCidly38Zlq6tfx6voNAHQoA?annotation_id=annotation_2115035321&amp;ei=bGU9XPCxJMqpgAfo0KGoBQ&amp;feature=iv&amp;src_vid=XjMorFcHC9Y&amp;sub_confirmation=1" link_class="5"/>
  </action>

</annotation>

<annotation id="annotation_2201211801" type="text" style="popup" log_data="l-class=5&amp;link=http%3A%2F%2Fwww.youtube.com%2Fuser%2FLeFloid%3Fsub_confirmation%3D1&amp;a-type=1&amp;a-v=XjMorFcHC9Y&amp;a-id=annotation_2201211801&amp;ei=bGU9XPCxJMqpgAfo0KGoBQ&amp;xble=1" itct="CAQQs-UBGP___________wEiEwjwl_Gm_e7fAhXKFOAKHWhoCFUo-B0yAml2SNaXnLjFlcqZXg">
  <TEXT>Abonnieren! Danke, geil Bro! :D</TEXT>
  <segment>
    <movingRegion type="rect">
      <rectRegion x="0.00000" y="0.00000" w="32.84500" h="6.91500" t="0:00.000"/>
      <rectRegion x="0.00000" y="0.00000" w="32.84500" h="6.91500" t="4:21.796"/>
    </movingRegion>
  </segment>
  <appearance bgAlpha="0.25" bgColor="0" fgColor="16777215" textSize="3.3098083333333332" effects="">
    
  </appearance>
  
  <action type="openUrl" trigger="click">
    <url target="new" value="https://www.youtube.com/user/LeFloid?annotation_id=annotation_2201211801&amp;ei=bGU9XPCxJMqpgAfo0KGoBQ&amp;feature=iv&amp;src_vid=XjMorFcHC9Y&amp;sub_confirmation=1" link_class="5"/>
  </action>

</annotation>
<annotation id="annotation_2399629149" type="text" style="highlightText" logable="false" itct="">
  
  <segment spaceRelative="annotation_2047159809">
    <movingRegion type="rect">
      <rectRegion x="0.00000" y="29.72200" w="25.00000" h="6.00000" t="never"/>
      <rectRegion x="0.00000" y="29.72200" w="25.00000" h="6.00000" t="never"/>
    </movingRegion>
  </segment>
  <appearance bgAlpha="0" textSize="3.911599999999999" highlightFontColor="0"/>
  <trigger>
    <condition ref="annotation_2047159809" state="rollOver"/>
  </trigger>
</annotation>

<annotation id="annotation_2678390569" type="text" style="highlightText" logable="false" itct="">
  
  <segment spaceRelative="annotation_2115035321">
    <movingRegion type="rect">
      <rectRegion x="0.00000" y="29.72200" w="25.00000" h="6.00000" t="never"/>
      <rectRegion x="0.00000" y="29.72200" w="25.00000" h="6.00000" t="never"/>
    </movingRegion>
  </segment>
  <appearance bgAlpha="0" textSize="3.911599999999999" highlightFontColor="0"/>
  <trigger>
    <condition ref="annotation_2115035321" state="rollOver"/>
  </trigger>
</annotation>

<annotation id="annotation_3392037077" type="text" style="popup" log_data="l-class=3&amp;link=http%3A%2F%2Fwww.youtube.com%2Fuser%2FDoktorFroid&amp;a-type=1&amp;a-v=XjMorFcHC9Y&amp;a-id=annotation_3392037077&amp;ei=bGU9XPCxJMqpgAfo0KGoBQ&amp;xble=1" itct="CAUQs-UBGP___________wEiEwjwl_Gm_e7fAhXKFOAKHWhoCFUo-B0yAml2SNaXnLjFlcqZXg">
  <TEXT>Gaming-Kanal! Check den! :3</TEXT>
  <segment>
    <movingRegion type="rect">
      <rectRegion x="32.80500" y="0.00000" w="31.26000" h="6.90100" t="0:00.000"/>
      <rectRegion x="32.80500" y="0.00000" w="31.26000" h="6.90100" t="4:21.796"/>
    </movingRegion>
  </segment>
  <appearance bgAlpha="0.25" bgColor="0" fgColor="16777215" textSize="3.3098083333333332" effects="">
    
  </appearance>
  
  <action type="openUrl" trigger="click">
    <url target="new" value="https://www.youtube.com/user/DoktorFroid?annotation_id=annotation_3392037077&amp;ei=bGU9XPCxJMqpgAfo0KGoBQ&amp;feature=iv&amp;src_vid=XjMorFcHC9Y" link_class="3"/>
  </action>

</annotation>
<annotation id="annotation_645283637" type="highlight" log_data="l-class=5&amp;link=http%3A%2F%2Fwww.youtube.com%2Fuser%2FDoktorFroid%3Fsub_confirmation%3D1&amp;a-type=3&amp;a-v=XjMorFcHC9Y&amp;a-id=annotation_645283637&amp;ei=bGU9XPCxJMqpgAfo0KGoBQ&amp;xble=1" itct="CAYQs-UBGP___________wEiEwjwl_Gm_e7fAhXKFOAKHWhoCFUo-B0yAml2SNaXnLjFlcqZXg">
  <segment>
    <movingRegion type="rect">
      <rectRegion x="68.78000" y="3.38000" w="25.00000" h="27.77800" t="4:21.796"/>
      <rectRegion x="68.78000" y="3.38000" w="25.00000" h="27.77800" t="4:57.494"/>
    </movingRegion>
  </segment>
  <appearance bgColor="16777215" highlightWidth="3" borderAlpha="0.2"/>
  
  <action type="openUrl" trigger="click">
    <url target="new" value="https://www.youtube.com/user/DoktorFroid?annotation_id=annotation_645283637&amp;ei=bGU9XPCxJMqpgAfo0KGoBQ&amp;feature=iv&amp;src_vid=XjMorFcHC9Y&amp;sub_confirmation=1" link_class="5"/>
  </action>

</annotation>

<annotation id="annotation_730190441" type="text" style="highlightText" logable="false" itct="">
  
  <segment spaceRelative="annotation_1070887645">
    <movingRegion type="rect">
      <rectRegion x="0.00000" y="29.72200" w="25.00000" h="6.00000" t="never"/>
      <rectRegion x="0.00000" y="29.72200" w="25.00000" h="6.00000" t="never"/>
    </movingRegion>
  </segment>
  <appearance bgAlpha="0" textSize="3.911599999999999" highlightFontColor="0"/>
  <trigger>
    <condition ref="annotation_1070887645" state="rollOver"/>
  </trigger>
</annotation>

<annotation id="annotation_745000991" type="text" style="highlightText" logable="false" itct="">
  
  <segment spaceRelative="annotation_645283637">
    <movingRegion type="rect">
      <rectRegion x="0.00000" y="29.72200" w="25.00000" h="6.00000" t="never"/>
      <rectRegion x="0.00000" y="29.72200" w="25.00000" h="6.00000" t="never"/>
    </movingRegion>
  </segment>
  <appearance bgAlpha="0" textSize="3.911599999999999" highlightFontColor="0"/>
  <trigger>
    <condition ref="annotation_645283637" state="rollOver"/>
  </trigger>
</annotation>

<annotation id="annotation_819645961" type="highlight" log_data="l-class=1&amp;link=http%3A%2F%2Fwww.youtube.com%2Fwatch%3Fv%3Dawi6ZbDXIj8%26list%3DUULm6s42r_wCbBX0QqXNCTwg%26index%3D2&amp;a-type=3&amp;a-v=XjMorFcHC9Y&amp;a-id=annotation_819645961&amp;ei=bGU9XPCxJMqpgAfo0KGoBQ&amp;xble=1" itct="">
  <segment>
    <movingRegion type="rect">
      <rectRegion x="14.89700" y="57.18300" w="30.54700" h="10.02800" t="4:21.796"/>
      <rectRegion x="14.89700" y="57.18300" w="30.54700" h="10.02800" t="4:57.494"/>
    </movingRegion>
  </segment>
  <appearance bgColor="16777215" highlightWidth="3" borderAlpha="0.2"/>
  
  <action type="openUrl" trigger="click">
    <url target="new" value="https://www.youtube.com/watch?annotation_id=annotation_819645961&amp;ei=bGU9XPCxJMqpgAfo0KGoBQ&amp;feature=iv&amp;index=2&amp;list=UULm6s42r_wCbBX0QqXNCTwg&amp;src_vid=XjMorFcHC9Y&amp;v=awi6ZbDXIj8" link_class="1"/>
  </action>

</annotation>
</annotations></document>