<?xml version="1.0" encoding="UTF-8" ?><document><annotations itct="CAAQwOYBIhMIs7rZpKbv3wIVVTDgCh3ATwzrKPgdMgJpdkjpgdHp_MWFsnc">
<annotation id="annotation_1591706969" type="highlight" log_data="ei=ZZA9XPPzNNXggAfAn7HYDg&amp;xble=1&amp;a-id=annotation_1591706969&amp;link=http%3A%2F%2Fwww.youtube.com%2Fwatch%3Fv%3DoFzRJzMsKHQ&amp;a-type=3&amp;l-class=1&amp;a-v=d2QWL800QOk" itct="CAEQs-UBGP___________wEiEwizutmkpu_fAhVVMOAKHcBPDOso-B0yAml2SOmB0en8xYWydw">
  <segment>
    <movingRegion type="rect">
      <rectRegion x="61.55100" y="54.08500" w="32.27800" h="37.73200" t="3:14.714"/>
      <rectRegion x="61.55100" y="54.08500" w="32.27800" h="37.73200" t="3:35.063"/>
    </movingRegion>
  </segment>
  <appearance bgColor="16777215" highlightWidth="3" borderAlpha="0.2"/>
  
  <action type="openUrl" trigger="click">
    <url target="current" value="https://www.youtube.com/watch?annotation_id=annotation_1591706969&amp;ei=ZZA9XPPzNNXggAfAn7HYDg&amp;feature=iv&amp;src_vid=d2QWL800QOk&amp;v=oFzRJzMsKHQ" link_class="1"/>
  </action>

</annotation>

<annotation id="annotation_2333016721" type="highlight" log_data="ei=ZZA9XPPzNNXggAfAn7HYDg&amp;xble=1&amp;a-id=annotation_2333016721&amp;link=http%3A%2F%2Fwww.youtube.com%2Fwatch%3Fv%3DhAGBR2O_c7o&amp;a-type=3&amp;l-class=1&amp;a-v=d2QWL800QOk" itct="CAIQs-UBGP___________wEiEwizutmkpu_fAhVVMOAKHcBPDOso-B0yAml2SOmB0en8xYWydw">
  <segment>
    <movingRegion type="rect">
      <rectRegion x="63.34700" y="8.45100" w="32.59500" h="37.35200" t="3:14.714"/>
      <rectRegion x="63.34700" y="8.45100" w="32.59500" h="37.35200" t="3:35.063"/>
    </movingRegion>
  </segment>
  <appearance bgColor="16777215" highlightWidth="3" borderAlpha="0.2"/>
  
  <action type="openUrl" trigger="click">
    <url target="current" value="https://www.youtube.com/watch?annotation_id=annotation_2333016721&amp;ei=ZZA9XPPzNNXggAfAn7HYDg&amp;feature=iv&amp;src_vid=d2QWL800QOk&amp;v=hAGBR2O_c7o" link_class="1"/>
  </action>

</annotation>

<annotation id="annotation_2696535885" type="text" style="highlightText" logable="false" itct="">
  
  <segment spaceRelative="annotation_1591706969">
    <movingRegion type="rect">
      <rectRegion x="0.00000" y="29.72200" w="25.00000" h="6.00000" t="never"/>
      <rectRegion x="0.00000" y="29.72200" w="25.00000" h="6.00000" t="never"/>
    </movingRegion>
  </segment>
  <appearance bgAlpha="0" textSize="3.911599999999999" highlightFontColor="0"/>
  <trigger>
    <condition ref="annotation_1591706969" state="rollOver"/>
  </trigger>
</annotation>

<annotation id="annotation_2811009697" type="text" style="highlightText" logable="false" itct="">
  
  <segment spaceRelative="annotation_3670416833">
    <movingRegion type="rect">
      <rectRegion x="0.00000" y="29.72200" w="25.00000" h="6.00000" t="never"/>
      <rectRegion x="0.00000" y="29.72200" w="25.00000" h="6.00000" t="never"/>
    </movingRegion>
  </segment>
  <appearance bgAlpha="0" textSize="3.911599999999999" highlightFontColor="0"/>
  <trigger>
    <condition ref="annotation_3670416833" state="rollOver"/>
  </trigger>
</annotation>

<annotation id="annotation_3509130795" type="text" style="highlightText" logable="false" itct="">
  
  <segment spaceRelative="annotation_849060015">
    <movingRegion type="rect">
      <rectRegion x="0.00000" y="29.72200" w="25.00000" h="6.00000" t="never"/>
      <rectRegion x="0.00000" y="29.72200" w="25.00000" h="6.00000" t="never"/>
    </movingRegion>
  </segment>
  <appearance bgAlpha="0" textSize="3.911599999999999" highlightFontColor="0"/>
  <trigger>
    <condition ref="annotation_849060015" state="rollOver"/>
  </trigger>
</annotation>

<annotation id="annotation_3670416833" type="highlight" log_data="ei=ZZA9XPPzNNXggAfAn7HYDg&amp;xble=1&amp;a-id=annotation_3670416833&amp;link=http%3A%2F%2Fwww.youtube.com%2Fuser%2Fspacefrogsplay&amp;a-type=3&amp;l-class=3&amp;a-v=d2QWL800QOk" itct="CAMQs-UBGP___________wEiEwizutmkpu_fAhVVMOAKHcBPDOso-B0yAml2SOmB0en8xYWydw">
  <segment>
    <movingRegion type="rect">
      <rectRegion x="29.58900" y="73.60600" w="11.92200" h="20.83400" t="3:14.714"/>
      <rectRegion x="29.58900" y="73.60600" w="11.92200" h="20.83400" t="3:35.063"/>
    </movingRegion>
  </segment>
  <appearance bgColor="16777215" highlightWidth="3" borderAlpha="0.2"/>
  
  <action type="openUrl" trigger="click">
    <url target="new" value="https://www.youtube.com/user/spacefrogsplay?annotation_id=annotation_3670416833&amp;ei=ZZA9XPPzNNXggAfAn7HYDg&amp;feature=iv&amp;src_vid=d2QWL800QOk" link_class="3"/>
  </action>

</annotation>

<annotation id="annotation_849060015" type="highlight" log_data="ei=ZZA9XPPzNNXggAfAn7HYDg&amp;xble=1&amp;a-id=annotation_849060015&amp;link=http%3A%2F%2Fwww.youtube.com%2Fuser%2Fspacefrogsent&amp;a-type=3&amp;l-class=3&amp;a-v=d2QWL800QOk" itct="CAQQs-UBGP___________wEiEwizutmkpu_fAhVVMOAKHcBPDOso-B0yAml2SOmB0en8xYWydw">
  <segment>
    <movingRegion type="rect">
      <rectRegion x="9.39100" y="67.78900" w="12.65800" h="23.08800" t="3:14.714"/>
      <rectRegion x="9.39100" y="67.78900" w="12.65800" h="23.08800" t="3:35.063"/>
    </movingRegion>
  </segment>
  <appearance bgColor="16777215" highlightWidth="3" borderAlpha="0.2"/>
  
  <action type="openUrl" trigger="click">
    <url target="new" value="https://www.youtube.com/user/spacefrogsent?annotation_id=annotation_849060015&amp;ei=ZZA9XPPzNNXggAfAn7HYDg&amp;feature=iv&amp;src_vid=d2QWL800QOk" link_class="3"/>
  </action>

</annotation>

<annotation id="annotation_987213569" type="text" style="highlightText" logable="false" itct="">
  
  <segment spaceRelative="annotation_2333016721">
    <movingRegion type="rect">
      <rectRegion x="0.00000" y="29.72200" w="25.00000" h="6.00000" t="never"/>
      <rectRegion x="0.00000" y="29.72200" w="25.00000" h="6.00000" t="never"/>
    </movingRegion>
  </segment>
  <appearance bgAlpha="0" textSize="3.911599999999999" highlightFontColor="0"/>
  <trigger>
    <condition ref="annotation_2333016721" state="rollOver"/>
  </trigger>
</annotation>
</annotations></document>