<?xml version="1.0" encoding="UTF-8" ?><document><annotations itct="CAAQwOYBIhMIp6Cjta7v3wIVC5J8Ch1x1wNpKPgdMgJpdkiFqaCkwfKyug0">
<annotation id="annotation_1264566553" type="text" style="highlightText" logable="false" itct="">
  
  <segment spaceRelative="annotation_3134690353">
    <movingRegion type="rect">
      <rectRegion x="-2.06000" y="16.63400" w="25.00000" h="6.00000" t="never"/>
      <rectRegion x="-2.06000" y="16.63400" w="25.00000" h="6.00000" t="never"/>
    </movingRegion>
  </segment>
  <appearance bgAlpha="0" textSize="3.911599999999999" highlightFontColor="0"/>
  <trigger>
    <condition ref="annotation_3134690353" state="rollOver"/>
  </trigger>
</annotation>

<annotation id="annotation_1330354481" type="text" style="highlightText" logable="false" itct="">
  
  <segment spaceRelative="annotation_3688789105">
    <movingRegion type="rect">
      <rectRegion x="-1.26800" y="19.43700" w="25.00000" h="6.00000" t="never"/>
      <rectRegion x="-1.26800" y="19.43700" w="25.00000" h="6.00000" t="never"/>
    </movingRegion>
  </segment>
  <appearance bgAlpha="0" textSize="3.911599999999999" highlightFontColor="0"/>
  <trigger>
    <condition ref="annotation_3688789105" state="rollOver"/>
  </trigger>
</annotation>

<annotation id="annotation_1538751681" type="highlight" log_data="link=http%3A%2F%2Fwww.alexibexi.de&amp;a-id=annotation_1538751681&amp;xble=1&amp;ei=7Jg9XKf6Bouk8gPxro_IBg&amp;a-v=DXTLlBSIFIU&amp;l-class=12&amp;a-type=3" itct="CAEQs-UBGP___________wEiEwinoKO1ru_fAhULknwKHXHXA2ko-B0yAml2SIWpoKTB8rK6DQ">
  <segment>
    <movingRegion type="rect">
      <rectRegion x="89.54000" y="16.05600" w="7.09200" h="15.94700" t="20:16.737"/>
      <rectRegion x="89.54000" y="16.05600" w="7.09200" h="15.94700" t="21:21.077"/>
    </movingRegion>
  </segment>
  <appearance bgColor="16777215" highlightWidth="3" borderAlpha="0.2"/>
  
  <action type="openUrl" trigger="click">
    <url target="new" value="http://www.alexibexi.de" link_class="12"/>
  </action>

</annotation>

<annotation id="annotation_1683789845" type="text" style="highlightText" logable="false" itct="">
  
  <segment spaceRelative="annotation_4057560975">
    <movingRegion type="rect">
      <rectRegion x="10.61800" y="18.59200" w="25.00000" h="6.00000" t="never"/>
      <rectRegion x="10.61800" y="18.59200" w="25.00000" h="6.00000" t="never"/>
    </movingRegion>
  </segment>
  <appearance bgAlpha="0" textSize="3.911599999999999" highlightFontColor="0"/>
  <trigger>
    <condition ref="annotation_4057560975" state="rollOver"/>
  </trigger>
</annotation>

<annotation id="annotation_1784922237" type="text" style="highlightText" logable="false" itct="">
  
  <segment spaceRelative="annotation_2126048121">
    <movingRegion type="rect">
      <rectRegion x="0.00000" y="29.72200" w="25.00000" h="6.00000" t="never"/>
      <rectRegion x="0.00000" y="29.72200" w="25.00000" h="6.00000" t="never"/>
    </movingRegion>
  </segment>
  <appearance bgAlpha="0" textSize="3.911599999999999" highlightFontColor="0"/>
  <trigger>
    <condition ref="annotation_2126048121" state="rollOver"/>
  </trigger>
</annotation>

<annotation id="annotation_199495087" type="text" style="highlightText" logable="false" itct="">
  
  <segment spaceRelative="annotation_3609286063">
    <movingRegion type="rect">
      <rectRegion x="0.00000" y="29.72200" w="25.00000" h="6.00000" t="never"/>
      <rectRegion x="0.00000" y="29.72200" w="25.00000" h="6.00000" t="never"/>
    </movingRegion>
  </segment>
  <appearance bgAlpha="0" textSize="3.911599999999999" highlightFontColor="0"/>
  <trigger>
    <condition ref="annotation_3609286063" state="rollOver"/>
  </trigger>
</annotation>

<annotation id="annotation_2004981733" type="highlight" log_data="link=http%3A%2F%2Fwww.instagram.com%2Falexibexi&amp;a-id=annotation_2004981733&amp;xble=1&amp;ei=7Jg9XKf6Bouk8gPxro_IBg&amp;a-v=DXTLlBSIFIU&amp;l-class=12&amp;a-type=3" itct="CAIQs-UBGP___________wEiEwinoKO1ru_fAhULknwKHXHXA2ko-B0yAml2SIWpoKTB8rK6DQ">
  <segment>
    <movingRegion type="rect">
      <rectRegion x="80.50700" y="16.05600" w="7.40900" h="15.66200" t="20:16.737"/>
      <rectRegion x="80.50700" y="16.05600" w="7.40900" h="15.66200" t="21:21.077"/>
    </movingRegion>
  </segment>
  <appearance bgColor="16777215" highlightWidth="3" borderAlpha="0.2"/>
  
  <action type="openUrl" trigger="click">
    <url target="new" value="http://www.instagram.com/alexibexi" link_class="12"/>
  </action>

</annotation>

<annotation id="annotation_2013774629" type="text" style="highlightText" logable="false" itct="">
  
  <segment spaceRelative="annotation_2004981733">
    <movingRegion type="rect">
      <rectRegion x="-7.60700" y="18.59200" w="25.00000" h="6.00000" t="never"/>
      <rectRegion x="-7.60700" y="18.59200" w="25.00000" h="6.00000" t="never"/>
    </movingRegion>
  </segment>
  <appearance bgAlpha="0" textSize="3.911599999999999" highlightFontColor="0"/>
  <trigger>
    <condition ref="annotation_2004981733" state="rollOver"/>
  </trigger>
</annotation>

<annotation id="annotation_2037106593" type="highlight" log_data="link=http%3A%2F%2Fwww.twitter.com%2Falextv&amp;a-id=annotation_2037106593&amp;xble=1&amp;ei=7Jg9XKf6Bouk8gPxro_IBg&amp;a-v=DXTLlBSIFIU&amp;l-class=14&amp;a-type=3" itct="CAMQs-UBGP___________wEiEwinoKO1ru_fAhULknwKHXHXA2ko-B0yAml2SIWpoKTB8rK6DQ">
  <segment>
    <movingRegion type="rect">
      <rectRegion x="61.49000" y="15.21100" w="8.51800" h="15.38400" t="20:16.737"/>
      <rectRegion x="61.49000" y="15.21100" w="8.51800" h="15.38400" t="21:21.077"/>
    </movingRegion>
  </segment>
  <appearance bgColor="16777215" highlightWidth="3" borderAlpha="0.2"/>
  
  <action type="openUrl" trigger="click">
    <url target="new" value="http://www.twitter.com/alextv" link_class="14"/>
  </action>

</annotation>

<annotation id="annotation_207429635" type="highlight" log_data="link=http%3A%2F%2Fwww.youtube.com%2Fwatch%3Fv%3D_Y6wB_PNV84&amp;a-id=annotation_207429635&amp;xble=1&amp;ei=7Jg9XKf6Bouk8gPxro_IBg&amp;a-v=DXTLlBSIFIU&amp;l-class=1&amp;a-type=3" itct="CAQQs-UBGP___________wEiEwinoKO1ru_fAhULknwKHXHXA2ko-B0yAml2SIWpoKTB8rK6DQ">
  <segment>
    <movingRegion type="rect">
      <rectRegion x="0.00000" y="73.52100" w="24.52500" h="25.24300" t="20:16.737"/>
      <rectRegion x="0.00000" y="73.52100" w="24.52500" h="25.24300" t="21:26.800"/>
    </movingRegion>
  </segment>
  <appearance bgColor="16777215" highlightWidth="3" borderAlpha="0.2"/>
  
  <action type="openUrl" trigger="click">
    <url target="current" value="https://www.youtube.com/watch?annotation_id=annotation_207429635&amp;ei=7Jg9XKf6Bouk8gPxro_IBg&amp;feature=iv&amp;src_vid=DXTLlBSIFIU&amp;v=_Y6wB_PNV84" link_class="1"/>
  </action>

</annotation>

<annotation id="annotation_2126048121" type="highlight" log_data="link=http%3A%2F%2Fwww.youtube.com%2Fwatch%3Fv%3Dn7KbBR8NbWo&amp;a-id=annotation_2126048121&amp;xble=1&amp;ei=7Jg9XKf6Bouk8gPxro_IBg&amp;a-v=DXTLlBSIFIU&amp;l-class=1&amp;a-type=3" itct="">
  <segment>
    <movingRegion type="rect">
      <rectRegion x="88.15400" y="74.46500" w="11.84600" h="25.53500" t="20:16.737"/>
      <rectRegion x="88.15400" y="74.46500" w="11.84600" h="25.53500" t="21:21.077"/>
    </movingRegion>
  </segment>
  <appearance bgColor="16777215" highlightWidth="3" borderAlpha="0.2"/>
  
  <action type="openUrl" trigger="click">
    <url target="current" value="https://www.youtube.com/watch?annotation_id=annotation_2126048121&amp;ei=7Jg9XKf6Bouk8gPxro_IBg&amp;feature=iv&amp;src_vid=DXTLlBSIFIU&amp;v=n7KbBR8NbWo" link_class="1"/>
  </action>

</annotation>

<annotation id="annotation_2726784743" type="text" style="highlightText" logable="false" itct="">
  
  <segment spaceRelative="annotation_1538751681">
    <movingRegion type="rect">
      <rectRegion x="-14.42200" y="17.18300" w="25.00000" h="6.00000" t="never"/>
      <rectRegion x="-14.42200" y="17.18300" w="25.00000" h="6.00000" t="never"/>
    </movingRegion>
  </segment>
  <appearance bgAlpha="0" textSize="3.911599999999999" highlightFontColor="0"/>
  <trigger>
    <condition ref="annotation_1538751681" state="rollOver"/>
  </trigger>
</annotation>

<annotation id="annotation_2798434615" type="highlight" log_data="link=http%3A%2F%2Fwww.youtube.com%2Fwatch%3Fv%3D5E2K3iW-wpc&amp;a-id=annotation_2798434615&amp;xble=1&amp;ei=7Jg9XKf6Bouk8gPxro_IBg&amp;a-v=DXTLlBSIFIU&amp;l-class=1&amp;a-type=3" itct="">
  <segment>
    <movingRegion type="rect">
      <rectRegion x="25.51500" y="74.08500" w="24.20800" h="25.24300" t="20:16.737"/>
      <rectRegion x="25.51500" y="74.08500" w="24.20800" h="25.24300" t="21:21.077"/>
    </movingRegion>
  </segment>
  <appearance bgColor="16777215" highlightWidth="3" borderAlpha="0.2"/>
  
  <action type="openUrl" trigger="click">
    <url target="current" value="https://www.youtube.com/watch?annotation_id=annotation_2798434615&amp;ei=7Jg9XKf6Bouk8gPxro_IBg&amp;feature=iv&amp;src_vid=DXTLlBSIFIU&amp;v=5E2K3iW-wpc" link_class="1"/>
  </action>

</annotation>

<annotation id="annotation_3091999599" type="text" style="popup" log_data="a-v=DXTLlBSIFIU&amp;a-type=1&amp;a-id=annotation_3091999599&amp;xble=1&amp;ei=7Jg9XKf6Bouk8gPxro_IBg" itct="">
  <TEXT>twitter.com/alextv</TEXT>
  <segment>
    <movingRegion type="rect">
      <rectRegion x="82.40900" y="91.83100" w="17.63200" h="6.90900" t="0:00.000"/>
      <rectRegion x="82.40900" y="91.83100" w="17.63200" h="6.90900" t="21:26.800"/>
    </movingRegion>
  </segment>
  <appearance bgAlpha="0.25" bgColor="0" fgColor="16777215" textSize="3.3098083333333332" effects="">
    
  </appearance>
  
</annotation>
<annotation id="annotation_3134690353" type="highlight" log_data="link=http%3A%2F%2Fgplus.to%2Falexibexi&amp;a-id=annotation_3134690353&amp;xble=1&amp;ei=7Jg9XKf6Bouk8gPxro_IBg&amp;a-v=DXTLlBSIFIU&amp;l-class=12&amp;a-type=3" itct="">
  <segment>
    <movingRegion type="rect">
      <rectRegion x="70.99800" y="15.19700" w="7.40900" h="15.96100" t="20:16.737"/>
      <rectRegion x="70.99800" y="15.19700" w="7.40900" h="15.96100" t="21:21.077"/>
    </movingRegion>
  </segment>
  <appearance bgColor="16777215" highlightWidth="3" borderAlpha="0.2"/>
  
  <action type="openUrl" trigger="click">
    <url target="new" value="http://gplus.to/alexibexi" link_class="12"/>
  </action>

</annotation>

<annotation id="annotation_3533850665" type="highlight" log_data="link=http%3A%2F%2Fwww.youtube.com%2Fwatch%3Fv%3DFZsrPlmJaBo&amp;a-id=annotation_3533850665&amp;xble=1&amp;ei=7Jg9XKf6Bouk8gPxro_IBg&amp;a-v=DXTLlBSIFIU&amp;l-class=1&amp;a-type=3" itct="">
  <segment>
    <movingRegion type="rect">
      <rectRegion x="75.00000" y="74.36600" w="12.79700" h="25.24300" t="20:16.737"/>
      <rectRegion x="75.00000" y="74.36600" w="12.79700" h="25.24300" t="21:21.077"/>
    </movingRegion>
  </segment>
  <appearance bgColor="16777215" highlightWidth="3" borderAlpha="0.2"/>
  
  <action type="openUrl" trigger="click">
    <url target="current" value="https://www.youtube.com/watch?annotation_id=annotation_3533850665&amp;ei=7Jg9XKf6Bouk8gPxro_IBg&amp;feature=iv&amp;src_vid=DXTLlBSIFIU&amp;v=FZsrPlmJaBo" link_class="1"/>
  </action>

</annotation>

<annotation id="annotation_3609286063" type="highlight" log_data="link=http%3A%2F%2Fwww.youtube.com%2Fuser%2Falexibexi&amp;a-id=annotation_3609286063&amp;xble=1&amp;ei=7Jg9XKf6Bouk8gPxro_IBg&amp;a-v=DXTLlBSIFIU&amp;l-class=3&amp;a-type=3" itct="">
  <segment>
    <movingRegion type="rect">
      <rectRegion x="49.92100" y="73.90100" w="25.00000" h="26.09900" t="20:16.737"/>
      <rectRegion x="49.92100" y="73.90100" w="25.00000" h="26.09900" t="21:21.077"/>
    </movingRegion>
  </segment>
  <appearance bgColor="16777215" highlightWidth="3" borderAlpha="0.2"/>
  
  <action type="openUrl" trigger="click">
    <url target="current" value="https://www.youtube.com/user/alexibexi?annotation_id=annotation_3609286063&amp;ei=7Jg9XKf6Bouk8gPxro_IBg&amp;feature=iv&amp;src_vid=DXTLlBSIFIU" link_class="3"/>
  </action>

</annotation>

<annotation id="annotation_3688789105" type="highlight" log_data="link=http%3A%2F%2Fwww.facebook.com%2Falextv&amp;a-id=annotation_3688789105&amp;xble=1&amp;ei=7Jg9XKf6Bouk8gPxro_IBg&amp;a-v=DXTLlBSIFIU&amp;l-class=13&amp;a-type=3" itct="">
  <segment>
    <movingRegion type="rect">
      <rectRegion x="52.77300" y="16.33800" w="7.40900" h="15.10200" t="20:16.737"/>
      <rectRegion x="52.77300" y="16.33800" w="7.40900" h="15.10200" t="21:21.077"/>
    </movingRegion>
  </segment>
  <appearance bgColor="16777215" highlightWidth="3" borderAlpha="0.2"/>
  
  <action type="openUrl" trigger="click">
    <url target="new" value="http://www.facebook.com/alextv" link_class="13"/>
  </action>

</annotation>

<annotation id="annotation_4057560975" type="highlight" log_data="link=http%3A%2F%2Fwww.youtube.com%2Fuser%2Falexibexi%3Fsub_confirmation%3D1&amp;a-id=annotation_4057560975&amp;xble=1&amp;ei=7Jg9XKf6Bouk8gPxro_IBg&amp;a-v=DXTLlBSIFIU&amp;l-class=5&amp;a-type=3" itct="">
  <segment>
    <movingRegion type="rect">
      <rectRegion x="52.61500" y="42.53500" w="44.01700" h="17.07400" t="20:16.737"/>
      <rectRegion x="52.61500" y="42.53500" w="44.01700" h="17.07400" t="21:21.077"/>
    </movingRegion>
  </segment>
  <appearance bgColor="16777215" highlightWidth="3" borderAlpha="0.2"/>
  
  <action type="openUrl" trigger="click">
    <url target="new" value="https://www.youtube.com/user/alexibexi?annotation_id=annotation_4057560975&amp;ei=7Jg9XKf6Bouk8gPxro_IBg&amp;feature=iv&amp;src_vid=DXTLlBSIFIU&amp;sub_confirmation=1" link_class="5"/>
  </action>

</annotation>

<annotation id="annotation_540169383" type="text" style="popup" log_data="a-v=DXTLlBSIFIU&amp;a-type=1&amp;a-id=annotation_540169383&amp;xble=1&amp;ei=7Jg9XKf6Bouk8gPxro_IBg" itct="">
  <TEXT>facebook.de/alextv</TEXT>
  <segment>
    <movingRegion type="rect">
      <rectRegion x="0.00000" y="92.39400" w="19.69200" h="6.34500" t="0:00.000"/>
      <rectRegion x="0.00000" y="92.39400" w="19.69200" h="6.34500" t="21:26.800"/>
    </movingRegion>
  </segment>
  <appearance bgAlpha="0.25" bgColor="0" fgColor="16777215" textSize="3.911599999999999" effects="">
    
  </appearance>
  
</annotation>
<annotation id="annotation_701323213" type="text" style="highlightText" logable="false" itct="">
  
  <segment spaceRelative="annotation_207429635">
    <movingRegion type="rect">
      <rectRegion x="0.00000" y="29.72200" w="25.00000" h="6.00000" t="never"/>
      <rectRegion x="0.00000" y="29.72200" w="25.00000" h="6.00000" t="never"/>
    </movingRegion>
  </segment>
  <appearance bgAlpha="0" textSize="3.911599999999999" highlightFontColor="0"/>
  <trigger>
    <condition ref="annotation_207429635" state="rollOver"/>
  </trigger>
</annotation>

<annotation id="annotation_922460975" type="text" style="highlightText" logable="false" itct="">
  
  <segment spaceRelative="annotation_3533850665">
    <movingRegion type="rect">
      <rectRegion x="0.00000" y="29.72200" w="25.00000" h="6.00000" t="never"/>
      <rectRegion x="0.00000" y="29.72200" w="25.00000" h="6.00000" t="never"/>
    </movingRegion>
  </segment>
  <appearance bgAlpha="0" textSize="3.911599999999999" highlightFontColor="0"/>
  <trigger>
    <condition ref="annotation_3533850665" state="rollOver"/>
  </trigger>
</annotation>

<annotation id="annotation_924468343" type="text" style="highlightText" logable="false" itct="">
  
  <segment spaceRelative="annotation_2798434615">
    <movingRegion type="rect">
      <rectRegion x="0.00000" y="29.72200" w="25.00000" h="6.00000" t="never"/>
      <rectRegion x="0.00000" y="29.72200" w="25.00000" h="6.00000" t="never"/>
    </movingRegion>
  </segment>
  <appearance bgAlpha="0" textSize="3.911599999999999" highlightFontColor="0"/>
  <trigger>
    <condition ref="annotation_2798434615" state="rollOver"/>
  </trigger>
</annotation>

<annotation id="annotation_994755635" type="text" style="highlightText" logable="false" itct="">
  
  <segment spaceRelative="annotation_2037106593">
    <movingRegion type="rect">
      <rectRegion x="-2.69400" y="19.43700" w="25.00000" h="6.00000" t="never"/>
      <rectRegion x="-2.69400" y="19.43700" w="25.00000" h="6.00000" t="never"/>
    </movingRegion>
  </segment>
  <appearance bgAlpha="0" textSize="3.911599999999999" highlightFontColor="0"/>
  <trigger>
    <condition ref="annotation_2037106593" state="rollOver"/>
  </trigger>
</annotation>

<annotation id="channel:53d76bbb-0000-2ecf-88c3-001a1140dcae" style="branding" type="branding"
            log_data="link-id=UCzH549YlZhdhIqhtvz7XHmQ&amp;a-id=53d76bbb-0000-2ecf-88c3-001a1140dcae&amp;xble=0&amp;ei=7Jg9XKf6Bouk8gPxro_IBg&amp;a-v=DXTLlBSIFIU&amp;l-class=3&amp;a-ch=UCzH549YlZhdhIqhtvz7XHmQ&amp;a-type=10">
  <data>{&quot;image_type&quot;:1,&quot;channel_id&quot;:&quot;UCzH549YlZhdhIqhtvz7XHmQ&quot;,&quot;session_data&quot;:{&quot;annotation_id&quot;:&quot;53d76bbb-0000-2ecf-88c3-001a1140dcae&quot;,&quot;src_vid&quot;:&quot;DXTLlBSIFIU&quot;,&quot;itct&quot;:&quot;CAUQ8zcY____________ASITCKego7Wu798CFQuSfAodcdcDaSj4HTICaXZIhamgpMHysroN&quot;,&quot;feature&quot;:&quot;iv&quot;,&quot;ei&quot;:&quot;7Jg9XKf6Bouk8gPxro_IBg&quot;},&quot;start_ms&quot;:0,&quot;num_subscribers&quot;:&quot;1338198&quot;,&quot;is_mobile&quot;:false,&quot;image_url&quot;:&quot;https:\/\/i.ytimg.com\/an\/zH549YlZhdhIqhtvz7XHmQ\/featured_channel.jpg?v=53de02fb&quot;,&quot;image_width&quot;:40,&quot;end_ms&quot;:1287000,&quot;channel_name&quot;:&quot;AlexiBexi&quot;,&quot;image_height&quot;:40,&quot;use_standalone_subscribe_button&quot;:true,&quot;standalone_subscribe_button_data&quot;:{&quot;unsubscribeCount&quot;:&quot;1,3\u00a0Mio.&quot;,&quot;subscribeText&quot;:&quot;Abonnieren&quot;,&quot;subscribed&quot;:false,&quot;unsubscribeText&quot;:&quot;Abonniert&quot;,&quot;subscribeCount&quot;:&quot;1,3\u00a0Mio.&quot;,&quot;signinUrl&quot;:&quot;https:\/\/accounts.google.com\/ServiceLogin?passive=true\u0026continue=http%3A%2F%2Fwww.youtube.com%2Fsignin%3Fapp%3Ddesktop%26action_handle_signin%3Dtrue%26next%3Dhttps%253A%252F%252Fwww.youtube.com%252Fuser%252FAlexiBexi%26continue_action%3DQUFFLUhqa25aWjl2aWpiblRNZEo1T2xWenAzYVNSQzVMZ3xBQ3Jtc0tuLWlwbV9HUkoxZlM5RF9Za0p5Y1o0SlYyRzFHY29mWGhZVXhocHhPWHhiR21qR2gwdlBCay1ocXlTNVBYeE9oelg1aGtZNkxTeVdIRmNGdHRDOFdDQXZqMy00MTNBWnFsbHM0VXZrMzN3RUVfNElXUm54V1E4eFpieEdHWVd2NTF0TVF4RzVzNTEzWXdHb1p3Y0VVUmxSSnp6QXQ2SWFZYnpHRVgtX2pxMlc4R2lZZ2VjNDB3OHAxV2l0bF9nT3g2SGZvNFRWMVo4aVhYdkhuQkcweWxtVHVnZlhRLTdPNlpPWHdEVUJtWktURUkyRTRB%26hl%3Dde%26feature%3Div\u0026uilel=3\u0026service=youtube\u0026hl=de&quot;,&quot;classic&quot;:true,&quot;enabled&quot;:false,&quot;feature&quot;:&quot;iv&quot;},&quot;subscription_token&quot;:[&quot;&quot;,&quot;&quot;]}</data>
  <segment/>
  <action trigger="click" type="openUrl">
    <url type="hyperlink" target="new" value="https://www.youtube.com/user/AlexiBexi"/>
  </action>
</annotation></annotations></document>