<?xml version="1.0" encoding="UTF-8" ?><document><annotations itct="CAAQwOYBIhMIqOmVxNru3wIVDIPeCh163gtmKPgdMgJpdkiyqNCEqcqux2A">
<annotation id="annotation_309717" type="text" style="popup" log_data="a-id=annotation_309717&amp;ei=9kA9XKiWL4yG-gb6vK-wBg&amp;xble=1&amp;a-v=YI66UpCUFDI&amp;a-type=1" itct="CAEQs-UBGP___________wEiEwio6ZXE2u7fAhUMg94KHXreC2Yo-B0yAml2SLKo0ISpyq7HYA">
  <TEXT>CreativeGamingClerks wird eingestellt - spart euch also das Abo! :D</TEXT>
  <segment>
    <movingRegion type="rect">
      <rectRegion x="15.00000" y="68.88900" w="71.25000" h="8.88900" t="0:03:46.3"/>
      <rectRegion x="15.00000" y="68.88900" w="71.25000" h="8.88900" t="0:03:52.8"/>
    </movingRegion>
  </segment>
  <appearance bgAlpha="0.600000023842" bgColor="14562356" fgColor="16777215" textSize="3.9116" effects="textdropshadow">
    <padding top="2.34696006775" left="1.32016503811" bottom="2.34696006775" right="1.76022005081"/>
  </appearance>
  
</annotation></annotations></document>