<?xml version="1.0" encoding="UTF-8" ?><document><annotations itct="CAAQwOYBIhMIhrCqzZTv3wIVAXPgCh3YQAeBKPgdMgJpdkjGorj_-NbslWA">
<annotation id="annotation_1288598073" type="highlight" log_data="xble=1&amp;l-class=1&amp;a-id=annotation_1288598073&amp;link=http%3A%2F%2Fwww.youtube.com%2Fwatch%3Fv%3D9HH-asvLAj4&amp;a-type=3&amp;a-v=YCuyt4_uEUY&amp;ei=2309XMbWDoHmgQfYgZ2ICA" itct="CAEQs-UBGP___________wEiEwiGsKrNlO_fAhUBc-AKHdhAB4Eo-B0yAml2SMaiuP_41uyVYA">
  <segment>
    <movingRegion type="rect">
      <rectRegion x="10.93500" y="2.81700" w="36.25200" h="32.56300" t="6:38.034"/>
      <rectRegion x="10.93500" y="2.81700" w="36.25200" h="32.56300" t="6:51.572"/>
    </movingRegion>
  </segment>
  <appearance bgColor="14562356" highlightWidth="3" borderAlpha="0.2"/>
  
  <action type="openUrl" trigger="click">
    <url target="new" value="https://www.youtube.com/watch?annotation_id=annotation_1288598073&amp;ei=2309XMbWDoHmgQfYgZ2ICA&amp;feature=iv&amp;src_vid=YCuyt4_uEUY&amp;v=9HH-asvLAj4" link_class="1"/>
  </action>

</annotation>

<annotation id="annotation_1614829519" type="highlight" log_data="xble=1&amp;l-class=1&amp;a-id=annotation_1614829519&amp;link=http%3A%2F%2Fwww.youtube.com%2Fwatch%3Fv%3DHZzdXR0bV8o&amp;a-type=3&amp;a-v=YCuyt4_uEUY&amp;ei=2309XMbWDoHmgQfYgZ2ICA" itct="CAIQs-UBGP___________wEiEwiGsKrNlO_fAhUBc-AKHdhAB4Eo-B0yAml2SMaiuP_41uyVYA">
  <segment>
    <movingRegion type="rect">
      <rectRegion x="52.77300" y="43.09900" w="36.25200" h="32.00000" t="6:38.289"/>
      <rectRegion x="52.77300" y="43.09900" w="36.25200" h="32.00000" t="6:51.572"/>
    </movingRegion>
  </segment>
  <appearance bgColor="14562356" highlightWidth="3" borderAlpha="0.2"/>
  
  <action type="openUrl" trigger="click">
    <url target="new" value="https://www.youtube.com/watch?annotation_id=annotation_1614829519&amp;ei=2309XMbWDoHmgQfYgZ2ICA&amp;feature=iv&amp;src_vid=YCuyt4_uEUY&amp;v=HZzdXR0bV8o" link_class="1"/>
  </action>

</annotation>

<annotation id="annotation_3039330767" type="highlight" log_data="xble=1&amp;l-class=1&amp;a-id=annotation_3039330767&amp;link=http%3A%2F%2Fwww.youtube.com%2Fwatch%3Fv%3D7U-RbOKanYs&amp;a-type=3&amp;a-v=YCuyt4_uEUY&amp;ei=2309XMbWDoHmgQfYgZ2ICA" itct="CAMQs-UBGP___________wEiEwiGsKrNlO_fAhUBc-AKHdhAB4Eo-B0yAml2SMaiuP_41uyVYA">
  <segment>
    <movingRegion type="rect">
      <rectRegion x="11.25200" y="42.81700" w="35.93500" h="32.28200" t="6:38.034"/>
      <rectRegion x="11.25200" y="42.81700" w="35.93500" h="32.28200" t="6:51.572"/>
    </movingRegion>
  </segment>
  <appearance bgColor="14562356" highlightWidth="3" borderAlpha="0.2"/>
  
  <action type="openUrl" trigger="click">
    <url target="new" value="https://www.youtube.com/watch?annotation_id=annotation_3039330767&amp;ei=2309XMbWDoHmgQfYgZ2ICA&amp;feature=iv&amp;src_vid=YCuyt4_uEUY&amp;v=7U-RbOKanYs" link_class="1"/>
  </action>

</annotation>

<annotation id="annotation_3279422457" type="highlight" log_data="xble=1&amp;l-class=1&amp;a-id=annotation_3279422457&amp;link=http%3A%2F%2Fwww.youtube.com%2Fwatch%3Fv%3DzFb4tilDmBg&amp;a-type=3&amp;a-v=YCuyt4_uEUY&amp;ei=2309XMbWDoHmgQfYgZ2ICA" itct="CAQQs-UBGP___________wEiEwiGsKrNlO_fAhUBc-AKHdhAB4Eo-B0yAml2SMaiuP_41uyVYA">
  <segment>
    <movingRegion type="rect">
      <rectRegion x="53.09000" y="2.81700" w="35.93500" h="31.71800" t="6:38.289"/>
      <rectRegion x="53.09000" y="2.81700" w="35.93500" h="31.71800" t="6:51.572"/>
    </movingRegion>
  </segment>
  <appearance bgColor="14562356" highlightWidth="3" borderAlpha="0.2"/>
  
  <action type="openUrl" trigger="click">
    <url target="new" value="https://www.youtube.com/watch?annotation_id=annotation_3279422457&amp;ei=2309XMbWDoHmgQfYgZ2ICA&amp;feature=iv&amp;src_vid=YCuyt4_uEUY&amp;v=zFb4tilDmBg" link_class="1"/>
  </action>

</annotation>

<annotation id="annotation_337721359" type="text" style="highlightText" logable="false" itct="">
  <TEXT>Gamer&#39;s Paradise</TEXT>
  <segment spaceRelative="annotation_1614829519">
    <movingRegion type="rect">
      <rectRegion x="0.00000" y="25.77500" w="34.98400" h="9.94700" t="never"/>
      <rectRegion x="0.00000" y="25.77500" w="34.98400" h="9.94700" t="never"/>
    </movingRegion>
  </segment>
  <appearance bgAlpha="0" textSize="4.814266666666667" highlightFontColor="16777215"/>
  <trigger>
    <condition ref="annotation_1614829519" state="rollOver"/>
  </trigger>
</annotation>

<annotation id="annotation_377251847" type="text" style="highlightText" logable="false" itct="">
  <TEXT>Computing Aladdin&#39;s Cave</TEXT>
  <segment spaceRelative="annotation_3279422457">
    <movingRegion type="rect">
      <rectRegion x="0.00000" y="26.33800" w="35.93500" h="9.38400" t="never"/>
      <rectRegion x="0.00000" y="26.33800" w="35.93500" h="9.38400" t="never"/>
    </movingRegion>
  </segment>
  <appearance bgAlpha="0" textSize="4.814266666666667" highlightFontColor="16777215"/>
  <trigger>
    <condition ref="annotation_3279422457" state="rollOver"/>
  </trigger>
</annotation>

<annotation id="annotation_3773247443" type="text" style="highlightText" logable="false" itct="">
  <TEXT>Colossus &amp; Bletchley Park</TEXT>
  <segment spaceRelative="annotation_1288598073">
    <movingRegion type="rect">
      <rectRegion x="0.00000" y="26.62000" w="36.09400" h="9.10200" t="never"/>
      <rectRegion x="0.00000" y="26.62000" w="36.09400" h="9.10200" t="never"/>
    </movingRegion>
  </segment>
  <appearance bgAlpha="0" textSize="4.814266666666667" highlightFontColor="16777215"/>
  <trigger>
    <condition ref="annotation_1288598073" state="rollOver"/>
  </trigger>
</annotation>

<annotation id="annotation_3842709371" type="text" style="highlightText" logable="false" itct="">
  <TEXT>Password Cracking on 4x Titan X Beast</TEXT>
  <segment spaceRelative="annotation_3039330767">
    <movingRegion type="rect">
      <rectRegion x="4.12000" y="18.73200" w="28.96200" h="16.99000" t="never"/>
      <rectRegion x="4.12000" y="18.73200" w="28.96200" h="16.99000" t="never"/>
    </movingRegion>
  </segment>
  <appearance bgAlpha="0" textSize="4.814266666666667" highlightFontColor="16777215"/>
  <trigger>
    <condition ref="annotation_3039330767" state="rollOver"/>
  </trigger>
</annotation>

<annotation id="channel:56a7cd8a-0000-2aea-9483-94eb2c05d02e" style="branding" type="branding"
            log_data="xble=0&amp;l-class=3&amp;a-ch=UC9-y-6csu5WGm29I7JiwpnA&amp;a-id=56a7cd8a-0000-2aea-9483-94eb2c05d02e&amp;a-type=10&amp;link-id=UC9-y-6csu5WGm29I7JiwpnA&amp;a-v=YCuyt4_uEUY&amp;ei=2309XMbWDoHmgQfYgZ2ICA">
  <data>{&quot;end_ms&quot;:412000,&quot;session_data&quot;:{&quot;feature&quot;:&quot;iv&quot;,&quot;itct&quot;:&quot;CAUQ8zcY____________ASITCIawqs2U798CFQFz4Aod2EAHgSj4HTICaXZIxqK4__jW7JVg&quot;,&quot;ei&quot;:&quot;2309XMbWDoHmgQfYgZ2ICA&quot;,&quot;src_vid&quot;:&quot;YCuyt4_uEUY&quot;,&quot;annotation_id&quot;:&quot;56a7cd8a-0000-2aea-9483-94eb2c05d02e&quot;},&quot;use_standalone_subscribe_button&quot;:true,&quot;image_url&quot;:&quot;https:\/\/i.ytimg.com\/an\/9-y-6csu5WGm29I7JiwpnA\/featured_channel.jpg?v=56aa1811&quot;,&quot;channel_name&quot;:&quot;Computerphile&quot;,&quot;start_ms&quot;:5000,&quot;num_subscribers&quot;:&quot;1272336&quot;,&quot;subscription_token&quot;:[&quot;&quot;,&quot;&quot;],&quot;standalone_subscribe_button_data&quot;:{&quot;unsubscribeText&quot;:&quot;Abonniert&quot;,&quot;subscribed&quot;:false,&quot;signinUrl&quot;:&quot;https:\/\/accounts.google.com\/ServiceLogin?service=youtube\u0026continue=http%3A%2F%2Fwww.youtube.com%2Fsignin%3Fcontinue_action%3DQUFFLUhqbHpySVNjSzlmdXN1SjBPRUhRUEt6cW54UElOd3xBQ3Jtc0tsRkRuUW03R1pydWxaaUdHSXlBM281U2w2eHI1elhmX3NEeDZydjNWdXNub21QNmxveWpaTnl2V2hrNm0zWUZLaUNNbFZxNnU4eG9HUWU2UVNJbWMtUG1Yb2FBOUFJd3NzaTlISGpGblhROGNydlU1YkEyT2sxTWJVVkU3aHlHcUhKOWVudk0zU3VuQm9iaXFac2JLRW1fMFRleHpQSk9semJjYXNPNDJLZDY2RjJuXzdwd3BnQXJDYm5ZazhCdUxLZTJjd0c5VExFLWNDSXJydlhKTFVBVklndkdxQVdUbmVJT0JZVzZpRFgyZUdMejd3%26action_handle_signin%3Dtrue%26next%3Dhttps%253A%252F%252Fwww.youtube.com%252Fuser%252FComputerphile%26hl%3Dde%26feature%3Div%26app%3Ddesktop\u0026hl=de\u0026uilel=3\u0026passive=true&quot;,&quot;subscribeCount&quot;:&quot;1,2\u00a0Mio.&quot;,&quot;enabled&quot;:false,&quot;subscribeText&quot;:&quot;Abonnieren&quot;,&quot;classic&quot;:true,&quot;unsubscribeCount&quot;:&quot;1,2\u00a0Mio.&quot;,&quot;feature&quot;:&quot;iv&quot;},&quot;image_type&quot;:1,&quot;image_height&quot;:23,&quot;channel_id&quot;:&quot;UC9-y-6csu5WGm29I7JiwpnA&quot;,&quot;image_width&quot;:51,&quot;is_mobile&quot;:false}</data>
  <segment/>
  <action trigger="click" type="openUrl">
    <url type="hyperlink" target="new" value="https://www.youtube.com/user/Computerphile"/>
  </action>
</annotation>
<annotation id="video:a17c5fcd-cbd1-4451-aaae-78e6c42cacba" style="video" type="card" log_data="a-ch=UC9-y-6csu5WGm29I7JiwpnA&amp;a-id=a17c5fcd-cbd1-4451-aaae-78e6c42cacba&amp;a-type=62&amp;a-v=YCuyt4_uEUY&amp;ei=2309XMbWDoHmgQfYgZ2ICA&amp;l-class=1&amp;link-id=9HH-asvLAj4&amp;xble=0">
  <data>{&quot;tracking_params&quot;:{&quot;card&quot;:&quot;CAoQ1TYY____________ASITCIawqs2U798CFQFz4Aod2EAHgSj4HTIFY2FyZHNIxqK4__jW7JVg&quot;,&quot;icon&quot;:&quot;CAwQsJcBGP___________wEiEwiGsKrNlO_fAhUBc-AKHdhAB4Eo-B0yBWNhcmRzSMaiuP_41uyVYA&quot;,&quot;teaser&quot;:&quot;CAsQ0DYY____________ASITCIawqs2U798CFQFz4Aod2EAHgSj4HTIFY2FyZHNIxqK4__jW7JVg&quot;},&quot;end_ms&quot;:49712,&quot;session_data&quot;:{&quot;feature&quot;:&quot;cards&quot;,&quot;itct&quot;:&quot;CAoQ1TYY____________ASITCIawqs2U798CFQFz4Aod2EAHgSj4HTIFY2FyZHNIxqK4__jW7JVg&quot;,&quot;ei&quot;:&quot;2309XMbWDoHmgQfYgZ2ICA&quot;,&quot;src_vid&quot;:&quot;YCuyt4_uEUY&quot;,&quot;annotation_id&quot;:&quot;a17c5fcd-cbd1-4451-aaae-78e6c42cacba&quot;},&quot;pause_on_navigation&quot;:true,&quot;custom_message&quot;:&quot;&quot;,&quot;image_url&quot;:&quot;https:\/\/i.ytimg.com\/vi\/9HH-asvLAj4\/mqdefault.jpg&quot;,&quot;start_ms&quot;:49712,&quot;video_duration&quot;:&quot;8:42&quot;,&quot;meta_info&quot;:[&quot;von Computerphile&quot;,&quot;114.790 Aufrufe&quot;],&quot;url&quot;:&quot;https:\/\/www.youtube.com\/watch?v=9HH-asvLAj4&quot;,&quot;tracking&quot;:{&quot;teaser_click&quot;:[],&quot;close&quot;:[],&quot;impression&quot;:[],&quot;click&quot;:[],&quot;teaser_impression&quot;:[]},&quot;card_type&quot;:&quot;video&quot;,&quot;target&quot;:&quot;new&quot;,&quot;teaser_text&quot;:&quot;Empfohlen: Colossus \u0026 Bletchley Park - Computerphile&quot;,&quot;is_live_now&quot;:false,&quot;teaser_duration_ms&quot;:7000,&quot;timestamp&quot;:1469636356303,&quot;title&quot;:&quot;Colossus \u0026 Bletchley Park - Computerphile&quot;}</data>
  <segment/>
  <action trigger="click" type="openUrl">
    <url type="hyperlink" target="new" value="https://www.youtube.com/watch?v=9HH-asvLAj4"/>
  </action>
</annotation>

<annotation id="video:a0de9cbf-8fe2-470c-bce3-a235db008ae0" style="video" type="card" log_data="a-ch=UC9-y-6csu5WGm29I7JiwpnA&amp;a-id=a0de9cbf-8fe2-470c-bce3-a235db008ae0&amp;a-type=62&amp;a-v=YCuyt4_uEUY&amp;ei=2309XMbWDoHmgQfYgZ2ICA&amp;l-class=1&amp;link-id=d2NWPG2gB_A&amp;xble=0">
  <data>{&quot;tracking_params&quot;:{&quot;card&quot;:&quot;CA4Q1TYY____________ASITCIawqs2U798CFQFz4Aod2EAHgSj4HTIFY2FyZHNIxqK4__jW7JVg&quot;,&quot;icon&quot;:&quot;CBAQsJcBGP___________wEiEwiGsKrNlO_fAhUBc-AKHdhAB4Eo-B0yBWNhcmRzSMaiuP_41uyVYA&quot;,&quot;teaser&quot;:&quot;CA8Q0DYY____________ASITCIawqs2U798CFQFz4Aod2EAHgSj4HTIFY2FyZHNIxqK4__jW7JVg&quot;},&quot;end_ms&quot;:139658,&quot;session_data&quot;:{&quot;feature&quot;:&quot;cards&quot;,&quot;itct&quot;:&quot;CA4Q1TYY____________ASITCIawqs2U798CFQFz4Aod2EAHgSj4HTIFY2FyZHNIxqK4__jW7JVg&quot;,&quot;ei&quot;:&quot;2309XMbWDoHmgQfYgZ2ICA&quot;,&quot;src_vid&quot;:&quot;YCuyt4_uEUY&quot;,&quot;annotation_id&quot;:&quot;a0de9cbf-8fe2-470c-bce3-a235db008ae0&quot;},&quot;pause_on_navigation&quot;:true,&quot;custom_message&quot;:&quot;&quot;,&quot;image_url&quot;:&quot;https:\/\/i.ytimg.com\/vi\/d2NWPG2gB_A\/mqdefault.jpg&quot;,&quot;start_ms&quot;:139658,&quot;video_duration&quot;:&quot;19:00&quot;,&quot;meta_info&quot;:[&quot;von Computerphile&quot;,&quot;550.256 Aufrufe&quot;],&quot;url&quot;:&quot;https:\/\/www.youtube.com\/watch?v=d2NWPG2gB_A&quot;,&quot;tracking&quot;:{&quot;teaser_click&quot;:[],&quot;close&quot;:[],&quot;impression&quot;:[],&quot;click&quot;:[],&quot;teaser_impression&quot;:[]},&quot;card_type&quot;:&quot;video&quot;,&quot;target&quot;:&quot;new&quot;,&quot;teaser_text&quot;:&quot;Empfohlen: Turing&#39;s Enigma Problem (Part 1) - Computerphile&quot;,&quot;is_live_now&quot;:false,&quot;teaser_duration_ms&quot;:7000,&quot;timestamp&quot;:1469636389370,&quot;title&quot;:&quot;Turing&#39;s Enigma Problem (Part 1) - Computerphile&quot;}</data>
  <segment/>
  <action trigger="click" type="openUrl">
    <url type="hyperlink" target="new" value="https://www.youtube.com/watch?v=d2NWPG2gB_A"/>
  </action>
</annotation>

<annotation id="video:63a2f42e-0008-4c0b-b29e-cf4adc9e0b14" style="video" type="card" log_data="a-ch=UC9-y-6csu5WGm29I7JiwpnA&amp;a-id=63a2f42e-0008-4c0b-b29e-cf4adc9e0b14&amp;a-type=62&amp;a-v=YCuyt4_uEUY&amp;ei=2309XMbWDoHmgQfYgZ2ICA&amp;l-class=1&amp;link-id=Qbp3LJvcX38&amp;xble=0">
  <data>{&quot;tracking_params&quot;:{&quot;card&quot;:&quot;CBIQ1TYY____________ASITCIawqs2U798CFQFz4Aod2EAHgSj4HTIFY2FyZHNIxqK4__jW7JVg&quot;,&quot;icon&quot;:&quot;CBQQsJcBGP___________wEiEwiGsKrNlO_fAhUBc-AKHdhAB4Eo-B0yBWNhcmRzSMaiuP_41uyVYA&quot;,&quot;teaser&quot;:&quot;CBMQ0DYY____________ASITCIawqs2U798CFQFz4Aod2EAHgSj4HTIFY2FyZHNIxqK4__jW7JVg&quot;},&quot;end_ms&quot;:246878,&quot;session_data&quot;:{&quot;feature&quot;:&quot;cards&quot;,&quot;itct&quot;:&quot;CBIQ1TYY____________ASITCIawqs2U798CFQFz4Aod2EAHgSj4HTIFY2FyZHNIxqK4__jW7JVg&quot;,&quot;ei&quot;:&quot;2309XMbWDoHmgQfYgZ2ICA&quot;,&quot;src_vid&quot;:&quot;YCuyt4_uEUY&quot;,&quot;annotation_id&quot;:&quot;63a2f42e-0008-4c0b-b29e-cf4adc9e0b14&quot;},&quot;pause_on_navigation&quot;:true,&quot;custom_message&quot;:&quot;&quot;,&quot;image_url&quot;:&quot;https:\/\/i.ytimg.com\/vi\/Qbp3LJvcX38\/mqdefault.jpg&quot;,&quot;start_ms&quot;:246878,&quot;video_duration&quot;:&quot;10:00&quot;,&quot;meta_info&quot;:[&quot;von Computerphile&quot;,&quot;141.023 Aufrufe&quot;],&quot;url&quot;:&quot;https:\/\/www.youtube.com\/watch?v=Qbp3LJvcX38&quot;,&quot;tracking&quot;:{&quot;teaser_click&quot;:[],&quot;close&quot;:[],&quot;impression&quot;:[],&quot;click&quot;:[],&quot;teaser_impression&quot;:[]},&quot;card_type&quot;:&quot;video&quot;,&quot;target&quot;:&quot;new&quot;,&quot;teaser_text&quot;:&quot;Empfohlen: The Turing Test - Computerphile&quot;,&quot;is_live_now&quot;:false,&quot;teaser_duration_ms&quot;:7000,&quot;timestamp&quot;:1469636423644,&quot;title&quot;:&quot;The Turing Test - Computerphile&quot;}</data>
  <segment/>
  <action trigger="click" type="openUrl">
    <url type="hyperlink" target="new" value="https://www.youtube.com/watch?v=Qbp3LJvcX38"/>
  </action>
</annotation>

<annotation id="video:162b0680-3e72-4a29-b2e6-1320d2325abf" style="video" type="card" log_data="a-ch=UC9-y-6csu5WGm29I7JiwpnA&amp;a-id=162b0680-3e72-4a29-b2e6-1320d2325abf&amp;a-type=62&amp;a-v=YCuyt4_uEUY&amp;ei=2309XMbWDoHmgQfYgZ2ICA&amp;l-class=1&amp;link-id=G2_Q9FoD-oQ&amp;xble=0">
  <data>{&quot;tracking_params&quot;:{&quot;card&quot;:&quot;CBYQ1TYY____________ASITCIawqs2U798CFQFz4Aod2EAHgSj4HTIFY2FyZHNIxqK4__jW7JVg&quot;,&quot;icon&quot;:&quot;CBgQsJcBGP___________wEiEwiGsKrNlO_fAhUBc-AKHdhAB4Eo-B0yBWNhcmRzSMaiuP_41uyVYA&quot;,&quot;teaser&quot;:&quot;CBcQ0DYY____________ASITCIawqs2U798CFQFz4Aod2EAHgSj4HTIFY2FyZHNIxqK4__jW7JVg&quot;},&quot;end_ms&quot;:365194,&quot;session_data&quot;:{&quot;feature&quot;:&quot;cards&quot;,&quot;itct&quot;:&quot;CBYQ1TYY____________ASITCIawqs2U798CFQFz4Aod2EAHgSj4HTIFY2FyZHNIxqK4__jW7JVg&quot;,&quot;ei&quot;:&quot;2309XMbWDoHmgQfYgZ2ICA&quot;,&quot;src_vid&quot;:&quot;YCuyt4_uEUY&quot;,&quot;annotation_id&quot;:&quot;162b0680-3e72-4a29-b2e6-1320d2325abf&quot;},&quot;pause_on_navigation&quot;:true,&quot;custom_message&quot;:&quot;&quot;,&quot;image_url&quot;:&quot;https:\/\/i.ytimg.com\/vi\/G2_Q9FoD-oQ\/mqdefault.jpg&quot;,&quot;start_ms&quot;:365194,&quot;video_duration&quot;:&quot;11:52&quot;,&quot;meta_info&quot;:[&quot;von Numberphile&quot;,&quot;3.548.170 Aufrufe&quot;],&quot;url&quot;:&quot;https:\/\/www.youtube.com\/watch?v=G2_Q9FoD-oQ&quot;,&quot;tracking&quot;:{&quot;teaser_click&quot;:[],&quot;close&quot;:[],&quot;impression&quot;:[],&quot;click&quot;:[],&quot;teaser_impression&quot;:[]},&quot;card_type&quot;:&quot;video&quot;,&quot;target&quot;:&quot;new&quot;,&quot;teaser_text&quot;:&quot;Empfohlen: 158,962,555,217,826,360,000 (Enigma Machine) - Numberphile&quot;,&quot;is_live_now&quot;:false,&quot;teaser_duration_ms&quot;:7000,&quot;timestamp&quot;:1469636451391,&quot;title&quot;:&quot;158,962,555,217,826,360,000 (Enigma Machine) - Numberphile&quot;}</data>
  <segment/>
  <action trigger="click" type="openUrl">
    <url type="hyperlink" target="new" value="https://www.youtube.com/watch?v=G2_Q9FoD-oQ"/>
  </action>
</annotation>

<annotation id="video:dc4575cf-b656-48d6-aa35-d1fdccffba79" style="video" type="card" log_data="a-ch=UC9-y-6csu5WGm29I7JiwpnA&amp;a-id=dc4575cf-b656-48d6-aa35-d1fdccffba79&amp;a-type=62&amp;a-v=YCuyt4_uEUY&amp;ei=2309XMbWDoHmgQfYgZ2ICA&amp;l-class=1&amp;link-id=RPQD7-AOjMI&amp;xble=0">
  <data>{&quot;tracking_params&quot;:{&quot;card&quot;:&quot;CBoQ1TYY____________ASITCIawqs2U798CFQFz4Aod2EAHgSj4HTIFY2FyZHNIxqK4__jW7JVg&quot;,&quot;icon&quot;:&quot;CBwQsJcBGP___________wEiEwiGsKrNlO_fAhUBc-AKHdhAB4Eo-B0yBWNhcmRzSMaiuP_41uyVYA&quot;,&quot;teaser&quot;:&quot;CBsQ0DYY____________ASITCIawqs2U798CFQFz4Aod2EAHgSj4HTIFY2FyZHNIxqK4__jW7JVg&quot;},&quot;end_ms&quot;:397708,&quot;session_data&quot;:{&quot;feature&quot;:&quot;cards&quot;,&quot;itct&quot;:&quot;CBoQ1TYY____________ASITCIawqs2U798CFQFz4Aod2EAHgSj4HTIFY2FyZHNIxqK4__jW7JVg&quot;,&quot;ei&quot;:&quot;2309XMbWDoHmgQfYgZ2ICA&quot;,&quot;src_vid&quot;:&quot;YCuyt4_uEUY&quot;,&quot;annotation_id&quot;:&quot;dc4575cf-b656-48d6-aa35-d1fdccffba79&quot;},&quot;pause_on_navigation&quot;:true,&quot;custom_message&quot;:&quot;&quot;,&quot;image_url&quot;:&quot;https:\/\/i.ytimg.com\/vi\/RPQD7-AOjMI\/mqdefault.jpg&quot;,&quot;start_ms&quot;:397708,&quot;video_duration&quot;:&quot;6:26&quot;,&quot;meta_info&quot;:[&quot;von Computerphile&quot;,&quot;126.046 Aufrufe&quot;],&quot;url&quot;:&quot;https:\/\/www.youtube.com\/watch?v=RPQD7-AOjMI&quot;,&quot;tracking&quot;:{&quot;teaser_click&quot;:[],&quot;close&quot;:[],&quot;impression&quot;:[],&quot;click&quot;:[],&quot;teaser_impression&quot;:[]},&quot;card_type&quot;:&quot;video&quot;,&quot;target&quot;:&quot;new&quot;,&quot;teaser_text&quot;:&quot;Empfohlen: Turing Complete - Computerphile&quot;,&quot;is_live_now&quot;:false,&quot;teaser_duration_ms&quot;:7000,&quot;timestamp&quot;:1469636471743,&quot;title&quot;:&quot;Turing Complete - Computerphile&quot;}</data>
  <segment/>
  <action trigger="click" type="openUrl">
    <url type="hyperlink" target="new" value="https://www.youtube.com/watch?v=RPQD7-AOjMI"/>
  </action>
</annotation>

<annotation id="drawer" type="drawer">
  <segment/>
  <data>{
  &quot;iconTrackingParams&quot;: &quot;CAgQsJcBGP///////////wEiEwiGsKrNlO/fAhUBc+AKHdhAB4Eo+B0yBWNhcmRzSMaiuP/41uyVYA==&quot;, 
  &quot;closeTrackingParams&quot;: &quot;CAcQsZcBGP///////////wEiEwiGsKrNlO/fAhUBc+AKHdhAB4Eo+B0yBWNhcmRzSMaiuP/41uyVYA==&quot;, 
  &quot;headerText&quot;: &quot;Von Computerphile&quot;, 
  &quot;trackingParams&quot;: &quot;CAYQwjcY////////////ASITCIawqs2U798CFQFz4Aod2EAHgSj4HTIFY2FyZHNIxqK4//jW7JVg&quot;, 
  &quot;eventId&quot;: &quot;2309XMbWDoHmgQfYgZ2ICA&quot;
}</data>
</annotation>
</annotations></document>