<?xml version="1.0" encoding="UTF-8" ?><document><annotations itct="CAAQwOYBIhMIp8rI6-nu3wIVw4FVCh1xHg5bKPgdMgJpdkiYoYPCq-DUuXE">
<annotation id="annotation_1016251689" type="highlight" log_data="ei=A1E9XOe8OMOD1gLxvLjYBQ&amp;a-type=3&amp;link=http%3A%2F%2Fed.ted.com%2Fget_involved%23nominate-an-educator&amp;xble=1&amp;a-id=annotation_1016251689&amp;l-class=6&amp;a-v=cXNTArhA0Jg" itct="CAEQs-UBGP___________wEiEwinysjr6e7fAhXDgVUKHXEeDlso-B0yAml2SJihg8Kr4NS5cQ">
  <segment>
    <movingRegion type="rect">
      <rectRegion x="6.33900" y="70.98600" w="27.69400" h="19.89100" t="4:45.000"/>
      <rectRegion x="6.33900" y="70.98600" w="27.69400" h="19.89100" t="4:55.000"/>
    </movingRegion>
  </segment>
  <appearance bgColor="16777215" highlightWidth="3" borderAlpha="0.2"/>
  
  <action type="openUrl" trigger="click">
    <url target="new" value="http://ed.ted.com/get_involved#nominate-an-educator" link_class="6"/>
  </action>

</annotation>

<annotation id="annotation_1135764687" type="text" style="highlightText" logable="false" itct="">
  
  <segment spaceRelative="annotation_2166933131">
    <movingRegion type="rect">
      <rectRegion x="0.00000" y="21.04200" w="23.09800" h="8.25400" t="never"/>
      <rectRegion x="0.00000" y="21.04200" w="23.09800" h="8.25400" t="never"/>
    </movingRegion>
  </segment>
  <appearance bgAlpha="0" textSize="3.911599999999999" highlightFontColor="0"/>
  <trigger>
    <condition ref="annotation_2166933131" state="rollOver"/>
  </trigger>
</annotation>

<annotation id="annotation_1343182249" type="text" style="highlightText" logable="false" itct="">
  
  <segment spaceRelative="annotation_684359137">
    <movingRegion type="rect">
      <rectRegion x="0.00000" y="29.72200" w="25.00000" h="6.00000" t="never"/>
      <rectRegion x="0.00000" y="29.72200" w="25.00000" h="6.00000" t="never"/>
    </movingRegion>
  </segment>
  <appearance bgAlpha="0" textSize="3.911599999999999" highlightFontColor="0"/>
  <trigger>
    <condition ref="annotation_684359137" state="rollOver"/>
  </trigger>
</annotation>

<annotation id="annotation_1745819451" type="highlight" log_data="ei=A1E9XOe8OMOD1gLxvLjYBQ&amp;a-type=3&amp;link=http%3A%2F%2Fed.ted.com%2Fget_involved%23recommend-an-animator&amp;xble=1&amp;a-id=annotation_1745819451&amp;l-class=6&amp;a-v=cXNTArhA0Jg" itct="CAIQs-UBGP___________wEiEwinysjr6e7fAhXDgVUKHXEeDlso-B0yAml2SJihg8Kr4NS5cQ">
  <segment>
    <movingRegion type="rect">
      <rectRegion x="36.29200" y="70.42300" w="32.29000" h="19.89100" t="4:45.000"/>
      <rectRegion x="36.29200" y="70.42300" w="32.29000" h="19.89100" t="4:55.000"/>
    </movingRegion>
  </segment>
  <appearance bgColor="16777215" highlightWidth="3" borderAlpha="0.2"/>
  
  <action type="openUrl" trigger="click">
    <url target="new" value="http://ed.ted.com/get_involved#recommend-an-animator" link_class="6"/>
  </action>

</annotation>

<annotation id="annotation_2166933131" type="highlight" log_data="ei=A1E9XOe8OMOD1gLxvLjYBQ&amp;a-type=3&amp;link=http%3A%2F%2Fed.ted.com%2Fget_involved&amp;xble=1&amp;a-id=annotation_2166933131&amp;l-class=6&amp;a-v=cXNTArhA0Jg" itct="CAMQs-UBGP___________wEiEwinysjr6e7fAhXDgVUKHXEeDlso-B0yAml2SJihg8Kr4NS5cQ">
  <segment>
    <movingRegion type="rect">
      <rectRegion x="70.20600" y="70.70400" w="23.25700" h="21.01700" t="4:45.000"/>
      <rectRegion x="70.20600" y="70.70400" w="23.25700" h="21.01700" t="4:55.000"/>
    </movingRegion>
  </segment>
  <appearance bgColor="16777215" highlightWidth="3" borderAlpha="0.2"/>
  
  <action type="openUrl" trigger="click">
    <url target="new" value="http://ed.ted.com/get_involved" link_class="6"/>
  </action>

</annotation>

<annotation id="annotation_2515788027" type="text" style="highlightText" logable="false" itct="">
  
  <segment spaceRelative="annotation_1745819451">
    <movingRegion type="rect">
      <rectRegion x="0.00000" y="19.91500" w="32.29000" h="9.09900" t="never"/>
      <rectRegion x="0.00000" y="19.91500" w="32.29000" h="9.09900" t="never"/>
    </movingRegion>
  </segment>
  <appearance bgAlpha="0" textSize="3.911599999999999" highlightFontColor="0"/>
  <trigger>
    <condition ref="annotation_1745819451" state="rollOver"/>
  </trigger>
</annotation>

<annotation id="annotation_3030887991" type="text" style="popup" log_data="ei=A1E9XOe8OMOD1gLxvLjYBQ&amp;a-type=1&amp;link=https%3A%2F%2Fed.ted.com%2Flessons%2Fhow-interpreters-juggle-two-languages-at-once-ewandro-magalhaes&amp;xble=1&amp;a-id=annotation_3030887991&amp;l-class=12&amp;a-v=cXNTArhA0Jg" itct="CAQQs-UBGP___________wEiEwinysjr6e7fAhXDgVUKHXEeDlso-B0yAml2SJihg8Kr4NS5cQ">
  <TEXT>View full lesson on ed.ted.com</TEXT>
  <segment>
    <movingRegion type="rect">
      <rectRegion x="1.42600" y="3.94400" w="38.55000" h="8.88700" t="0:00.000"/>
      <rectRegion x="1.42600" y="3.94400" w="38.55000" h="8.88700" t="0:20.000"/>
    </movingRegion>
  </segment>
  <appearance bgAlpha="0.600000023842" bgColor="6710886" fgColor="16777215" textSize="3.911599999999999" effects="">
    
  </appearance>
  
  <action type="openUrl" trigger="click">
    <url target="new" value="https://ed.ted.com/lessons/how-interpreters-juggle-two-languages-at-once-ewandro-magalhaes" link_class="12"/>
  </action>

</annotation>
<annotation id="annotation_3192425071" type="text" style="popup" log_data="ei=A1E9XOe8OMOD1gLxvLjYBQ&amp;a-type=1&amp;link=http%3A%2F%2Fwww.youtube.com%2Fuser%2FTEDEducation%3Fsub_confirmation%3D1&amp;xble=1&amp;a-id=annotation_3192425071&amp;l-class=5&amp;a-v=cXNTArhA0Jg" itct="CAUQs-UBGP___________wEiEwinysjr6e7fAhXDgVUKHXEeDlso-B0yAml2SJihg8Kr4NS5cQ">
  <TEXT>Subscribe to TED-Ed</TEXT>
  <segment>
    <movingRegion type="rect">
      <rectRegion x="78.28800" y="12.95800" w="17.63900" h="26.63400" t="4:45.000"/>
      <rectRegion x="78.28800" y="12.95800" w="17.63900" h="26.63400" t="4:55.000"/>
    </movingRegion>
  </segment>
  <appearance bgAlpha="0.600000023842" bgColor="6710886" fgColor="16777215" textSize="3.911599999999999" effects="">
    
  </appearance>
  
  <action type="openUrl" trigger="click">
    <url target="new" value="https://www.youtube.com/user/TEDEducation?annotation_id=annotation_3192425071&amp;ei=A1E9XOe8OMOD1gLxvLjYBQ&amp;feature=iv&amp;src_vid=cXNTArhA0Jg&amp;sub_confirmation=1" link_class="5"/>
  </action>

</annotation>
<annotation id="annotation_360131401" type="text" style="highlightText" logable="false" itct="">
  
  <segment spaceRelative="annotation_1016251689">
    <movingRegion type="rect">
      <rectRegion x="0.00000" y="19.63400" w="27.53600" h="9.38000" t="never"/>
      <rectRegion x="0.00000" y="19.63400" w="27.53600" h="9.38000" t="never"/>
    </movingRegion>
  </segment>
  <appearance bgAlpha="0" textSize="3.911599999999999" highlightFontColor="0"/>
  <trigger>
    <condition ref="annotation_1016251689" state="rollOver"/>
  </trigger>
</annotation>

<annotation id="annotation_684359137" type="highlight" log_data="ei=A1E9XOe8OMOD1gLxvLjYBQ&amp;a-type=3&amp;link=https%3A%2F%2Fed.ted.com%2Flessons%2Fhow-interpreters-juggle-two-languages-at-once-ewandro-magalhaes&amp;xble=1&amp;a-id=annotation_684359137&amp;l-class=12&amp;a-v=cXNTArhA0Jg" itct="CAYQs-UBGP___________wEiEwinysjr6e7fAhXDgVUKHXEeDlso-B0yAml2SJihg8Kr4NS5cQ">
  <segment>
    <movingRegion type="rect">
      <rectRegion x="15.21400" y="53.52100" w="69.53200" h="13.69000" t="4:45.000"/>
      <rectRegion x="15.21400" y="53.52100" w="69.53200" h="13.69000" t="4:55.000"/>
    </movingRegion>
  </segment>
  <appearance bgColor="16777215" highlightWidth="3" borderAlpha="0.2"/>
  
  <action type="openUrl" trigger="click">
    <url target="new" value="https://ed.ted.com/lessons/how-interpreters-juggle-two-languages-at-once-ewandro-magalhaes" link_class="12"/>
  </action>

</annotation>

<annotation id="channel:51231490-0-2b0e-9082-47d7bdc088e" style="branding" type="branding"
            log_data="ei=A1E9XOe8OMOD1gLxvLjYBQ&amp;a-ch=UCsooa4yRKGN_zEE8iknghZA&amp;a-type=10&amp;xble=0&amp;link-id=UCsooa4yRKGN_zEE8iknghZA&amp;a-id=51231490-0-2b0e-9082-47d7bdc088e&amp;l-class=3&amp;a-v=cXNTArhA0Jg">
  <data>{&quot;standalone_subscribe_button_data&quot;:{&quot;unsubscribeText&quot;:&quot;Abonniert&quot;,&quot;feature&quot;:&quot;iv&quot;,&quot;subscribeText&quot;:&quot;Abonnieren&quot;,&quot;enabled&quot;:false,&quot;classic&quot;:true,&quot;unsubscribeCount&quot;:&quot;8,3\u00a0Mio.&quot;,&quot;subscribeCount&quot;:&quot;8,3\u00a0Mio.&quot;,&quot;subscribed&quot;:false,&quot;signinUrl&quot;:&quot;https:\/\/accounts.google.com\/ServiceLogin?hl=de\u0026service=youtube\u0026continue=http%3A%2F%2Fwww.youtube.com%2Fsignin%3Fhl%3Dde%26next%3Dhttps%253A%252F%252Fwww.youtube.com%252Fuser%252FTEDEducation%26continue_action%3DQUFFLUhqbWREeVBLTEZQbHhCZlZhM2dnNmhnZEJZVWZYUXxBQ3Jtc0tuTnZPLWNGbGZLdnVjU0R3SXB1RXVtNmZNUG1CN0hZTnZmQzJKNTJuNXpyWDRGNnJqWjcwVldrMzRBWUNMaDdTZzVmVmN6OExKdG1ha1NFWS1IWWlDN01kQ0RFdUpRMjR2THdVNDZkU1FVeUUtbkg2ektiUHVLY2R6R1dTY1o4YzhuSWtxbEN6VTNhcEs2X2U0MU1fOTluWlNhaHYzMzBuRGNDbVpBd3N4ZzY2dGVYbmx2SWxhQ3RVMm9icUFjRnYyR2d3ZjBHdlV6WTNMa1pFVTVFVWVMbi16SXlyN3FqNTIwUHZMTTBBaW1EVERmN2cw%26app%3Ddesktop%26feature%3Div%26action_handle_signin%3Dtrue\u0026passive=true\u0026uilel=3&quot;},&quot;session_data&quot;:{&quot;feature&quot;:&quot;iv&quot;,&quot;itct&quot;:&quot;CAcQ8zcY____________ASITCKfKyOvp7t8CFcOBVQodcR4OWyj4HTICaXZImKGDwqvg1Llx&quot;,&quot;ei&quot;:&quot;A1E9XOe8OMOD1gLxvLjYBQ&quot;,&quot;src_vid&quot;:&quot;cXNTArhA0Jg&quot;,&quot;annotation_id&quot;:&quot;51231490-0-2b0e-9082-47d7bdc088e&quot;},&quot;use_standalone_subscribe_button&quot;:true,&quot;image_width&quot;:40,&quot;end_ms&quot;:296000,&quot;is_mobile&quot;:false,&quot;image_height&quot;:40,&quot;num_subscribers&quot;:&quot;8355161&quot;,&quot;image_url&quot;:&quot;https:\/\/yt3.ggpht.com\/a-\/AAuE7mAALx0lu67j6r6P4OoUlMtR4FZO9xbT8PcyTw=s300-mo-c-c0xffffffff-rj-k-no&quot;,&quot;subscription_token&quot;:[&quot;&quot;,&quot;&quot;],&quot;start_ms&quot;:0,&quot;channel_name&quot;:&quot;TED-Ed&quot;,&quot;channel_id&quot;:&quot;UCsooa4yRKGN_zEE8iknghZA&quot;,&quot;image_type&quot;:0}</data>
  <segment/>
  <action trigger="click" type="openUrl">
    <url type="hyperlink" target="new" value="https://www.youtube.com/user/TEDEducation"/>
  </action>
</annotation></annotations></document>